{"apiVersion":"apps/v1","items":[{"apiVersion":"apps/v1","kind":"ReplicaSet","metadata":{"annotations":{"deployment.kubernetes.io/desired-replicas":"2","deployment.kubernetes.io/max-replicas":"3","deployment.kubernetes.io/revision":"1"},"creationTimestamp":"2022-07-23T14:09:43Z","generation":2,"labels":{"k8s-app":"kube-dns","kubernetes.io/cluster-service":"true","pod-template-hash":"87688dc49","version":"v20"},"name":"coredns-87688dc49","namespace":"kube-system","ownerReferences":[{"apiVersion":"apps/v1","blockOwnerDeletion":true,"controller":true,"kind":"Deployment","name":"coredns","uid":"a6258e3e-74cf-4092-9e21-55b733107093"}],"resourceVersion":"5177","uid":"1d431369-2c41-41fd-9a78-6f26d2f445cf"},"spec":{"replicas":2,"selector":{"matchLabels":{"k8s-app":"kube-dns","pod-template-hash":"87688dc49","version":"v20"}},"template":{"metadata":{"annotations":{"prometheus.io/port":"9153"},"creationTimestamp":null,"labels":{"k8s-app":"kube-dns","kubernetes.io/cluster-service":"true","pod-template-hash":"87688dc49","version":"v20"}},"spec":{"affinity":{"nodeAffinity":{"preferredDuringSchedulingIgnoredDuringExecution":[{"preference":{"matchExpressions":[{"key":"kubernetes.azure.com/mode","operator":"In","values":["system"]}]},"weight":100}]},"podAntiAffinity":{"preferredDuringSchedulingIgnoredDuringExecution":[{"podAffinityTerm":{"labelSelector":{"matchExpressions":[{"key":"k8s-app","operator":"In","values":["kube-dns"]}]},"topologyKey":"failure-domain.beta.kubernetes.io/zone"},"weight":10},{"podAffinityTerm":{"labelSelector":{"matchExpressions":[{"key":"k8s-app","operator":"In","values":["kube-dns"]}]},"topologyKey":"kubernetes.io/hostname"},"weight":5}]}},"containers":[{"args":["-conf","/etc/coredns/Corefile"],"image":"mcr.microsoft.com/oss/kubernetes/coredns:v1.8.7","imagePullPolicy":"IfNotPresent","livenessProbe":{"failureThreshold":5,"httpGet":{"path":"/health","port":8080,"scheme":"HTTP"},"initialDelaySeconds":60,"periodSeconds":10,"successThreshold":1,"timeoutSeconds":5},"name":"coredns","ports":[{"containerPort":53,"name":"dns","protocol":"UDP"},{"containerPort":53,"name":"dns-tcp","protocol":"TCP"},{"containerPort":9153,"name":"metrics","protocol":"TCP"}],"readinessProbe":{"failureThreshold":3,"httpGet":{"path":"/ready","port":8181,"scheme":"HTTP"},"periodSeconds":10,"successThreshold":1,"timeoutSeconds":1},"resources":{"limits":{"cpu":"3","memory":"500Mi"},"requests":{"cpu":"100m","memory":"70Mi"}},"securityContext":{"allowPrivilegeEscalation":false,"capabilities":{"add":["NET_BIND_SERVICE"],"drop":["all"]},"procMount":"Default","readOnlyRootFilesystem":true},"terminationMessagePath":"/dev/termination-log","terminationMessagePolicy":"File","volumeMounts":[{"mountPath":"/etc/coredns","name":"config-volume","readOnly":true},{"mountPath":"/etc/coredns/custom","name":"custom-config-volume","readOnly":true},{"mountPath":"/tmp","name":"tmp"}]}],"dnsPolicy":"Default","nodeSelector":{"beta.kubernetes.io/os":"linux"},"priorityClassName":"system-node-critical","restartPolicy":"Always","schedulerName":"default-scheduler","securityContext":{},"serviceAccount":"coredns","serviceAccountName":"coredns","terminationGracePeriodSeconds":30,"tolerations":[{"effect":"NoSchedule","key":"node-role.kubernetes.io/master"},{"key":"CriticalAddonsOnly","operator":"Exists"},{"effect":"NoExecute","key":"node.kubernetes.io/unreachable","operator":"Exists","tolerationSeconds":30},{"effect":"NoExecute","key":"node.kubernetes.io/not-ready","operator":"Exists","tolerationSeconds":30}],"volumes":[{"configMap":{"defaultMode":420,"items":[{"key":"Corefile","path":"Corefile"}],"name":"coredns"},"name":"config-volume"},{"configMap":{"defaultMode":420,"name":"coredns-custom","optional":true},"name":"custom-config-volume"},{"emptyDir":{},"name":"tmp"}]}}},"status":{"availableReplicas":2,"fullyLabeledReplicas":2,"observedGeneration":2,"readyReplicas":2,"replicas":2}},{"apiVersion":"apps/v1","kind":"ReplicaSet","metadata":{"annotations":{"deployment.kubernetes.io/desired-replicas":"1","deployment.kubernetes.io/max-replicas":"2","deployment.kubernetes.io/revision":"1"},"creationTimestamp":"2022-07-23T14:09:43Z","generation":1,"labels":{"k8s-app":"coredns-autoscaler","pod-template-hash":"84bdbbc855"},"name":"coredns-autoscaler-84bdbbc855","namespace":"kube-system","ownerReferences":[{"apiVersion":"apps/v1","blockOwnerDeletion":true,"controller":true,"kind":"Deployment","name":"coredns-autoscaler","uid":"ed9f9c36-e325-47f9-ad8c-046e09e4e0b6"}],"resourceVersion":"5189","uid":"3b73fb94-baa3-4712-a65a-af497965a758"},"spec":{"replicas":1,"selector":{"matchLabels":{"k8s-app":"coredns-autoscaler","pod-template-hash":"84bdbbc855"}},"template":{"metadata":{"annotations":{"cluster-autoscaler.kubernetes.io/safe-to-evict":"true","seccomp.security.alpha.kubernetes.io/pod":"runtime/default"},"creationTimestamp":null,"labels":{"k8s-app":"coredns-autoscaler","pod-template-hash":"84bdbbc855"}},"spec":{"affinity":{"nodeAffinity":{"preferredDuringSchedulingIgnoredDuringExecution":[{"preference":{"matchExpressions":[{"key":"kubernetes.azure.com/mode","operator":"In","values":["system"]}]},"weight":100}]}},"containers":[{"command":["/cluster-proportional-autoscaler","--namespace=kube-system","--configmap=coredns-autoscaler","--target=deployment/coredns","--default-params={\"ladder\":{\"coresToReplicas\":[[1,2],[512,3],[1024,4],[2048,5]],\"nodesToReplicas\":[[1,2],[8,3],[16,4],[32,5]]}}","--logtostderr=true","--v=2"],"image":"mcr.microsoft.com/oss/kubernetes/autoscaler/cluster-proportional-autoscaler:1.8.5","imagePullPolicy":"IfNotPresent","livenessProbe":{"failureThreshold":3,"httpGet":{"path":"/last-poll","port":8080,"scheme":"HTTP"},"initialDelaySeconds":10,"periodSeconds":10,"successThreshold":1,"timeoutSeconds":1},"name":"autoscaler","resources":{"limits":{"cpu":"200m","memory":"1G"},"requests":{"cpu":"20m","memory":"10Mi"}},"terminationMessagePath":"/dev/termination-log","terminationMessagePolicy":"File"}],"dnsPolicy":"Default","nodeSelector":{"beta.kubernetes.io/os":"linux"},"priorityClassName":"system-node-critical","restartPolicy":"Always","schedulerName":"default-scheduler","securityContext":{},"serviceAccount":"coredns-autoscaler","serviceAccountName":"coredns-autoscaler","terminationGracePeriodSeconds":30,"tolerations":[{"key":"CriticalAddonsOnly","operator":"Exists"},{"effect":"NoExecute","key":"node.kubernetes.io/unreachable","operator":"Exists","tolerationSeconds":30},{"effect":"NoExecute","key":"node.kubernetes.io/not-ready","operator":"Exists","tolerationSeconds":30}]}}},"status":{"availableReplicas":1,"fullyLabeledReplicas":1,"observedGeneration":1,"readyReplicas":1,"replicas":1}},{"apiVersion":"apps/v1","kind":"ReplicaSet","metadata":{"annotations":{"deployment.kubernetes.io/desired-replicas":"2","deployment.kubernetes.io/max-replicas":"2","deployment.kubernetes.io/revision":"1"},"creationTimestamp":"2022-07-23T14:09:43Z","generation":3,"labels":{"app":"konnectivity-agent","component":"tunnel","pod-template-hash":"6c6d576cb6"},"name":"konnectivity-agent-6c6d576cb6","namespace":"kube-system","ownerReferences":[{"apiVersion":"apps/v1","blockOwnerDeletion":true,"controller":true,"kind":"Deployment","name":"konnectivity-agent","uid":"89eee275-352b-4565-9433-60dc075ecd40"}],"resourceVersion":"1258","uid":"3bc135fd-888d-42a1-9af1-f0b8fd8e2752"},"spec":{"replicas":0,"selector":{"matchLabels":{"app":"konnectivity-agent","pod-template-hash":"6c6d576cb6"}},"template":{"metadata":{"annotations":{"checksum/client-cert":"bd46492bf0bb422a4a261940a97d545afee0b13872e6456ec557d59a9e010d90"},"creationTimestamp":null,"labels":{"app":"konnectivity-agent","component":"tunnel","pod-template-hash":"6c6d576cb6"}},"spec":{"affinity":{"nodeAffinity":{"preferredDuringSchedulingIgnoredDuringExecution":[{"preference":{"matchExpressions":[{"key":"kubernetes.azure.com/mode","operator":"In","values":["system"]}]},"weight":100}]},"podAntiAffinity":{"preferredDuringSchedulingIgnoredDuringExecution":[{"podAffinityTerm":{"labelSelector":{"matchExpressions":[{"key":"app","operator":"In","values":["konnectivity-agent"]}]},"topologyKey":"failure-domain.beta.kubernetes.io/zone"},"weight":10},{"podAffinityTerm":{"labelSelector":{"matchExpressions":[{"key":"app","operator":"In","values":["konnectivity-agent"]}]},"topologyKey":"kubernetes.io/hostname"},"weight":5}]}},"automountServiceAccountToken":false,"containers":[{"args":["--proxy-server-host=sonobuoy-test-dns-a72ecff9.hcp.canadacentral.azmk8s.io","--proxy-server-port=443","--health-server-port=8082","--keepalive-time=30s","--agent-key=/certs/client.key","--agent-cert=/certs/client.crt","--ca-cert=/certs/ca.crt","--alpn-proto=konnectivity","-v=2"],"command":["/proxy-agent"],"image":"mcr.microsoft.com/oss/kubernetes/apiserver-network-proxy/agent:v0.0.30","imagePullPolicy":"IfNotPresent","livenessProbe":{"failureThreshold":3,"httpGet":{"path":"/ready","port":8082,"scheme":"HTTP"},"initialDelaySeconds":30,"periodSeconds":60,"successThreshold":1,"timeoutSeconds":60},"name":"konnectivity-agent","readinessProbe":{"failureThreshold":3,"httpGet":{"path":"/ready","port":8082,"scheme":"HTTP"},"periodSeconds":10,"successThreshold":1,"timeoutSeconds":1},"resources":{"limits":{"cpu":"100m","memory":"128Mi"},"requests":{"cpu":"20m","memory":"20Mi"}},"terminationMessagePath":"/dev/termination-log","terminationMessagePolicy":"File","volumeMounts":[{"mountPath":"/certs","name":"certs"}]}],"dnsPolicy":"Default","nodeSelector":{"beta.kubernetes.io/os":"linux"},"priorityClassName":"system-node-critical","restartPolicy":"Always","schedulerName":"default-scheduler","securityContext":{},"serviceAccount":"konnectivity-agent","serviceAccountName":"konnectivity-agent","terminationGracePeriodSeconds":30,"tolerations":[{"key":"CriticalAddonsOnly","operator":"Exists"},{"effect":"NoExecute","key":"node.kubernetes.io/unreachable","operator":"Exists","tolerationSeconds":30},{"effect":"NoExecute","key":"node.kubernetes.io/not-ready","operator":"Exists","tolerationSeconds":30}],"volumes":[{"name":"certs","secret":{"defaultMode":420,"secretName":"konnectivity-certs"}}]}}},"status":{"observedGeneration":3,"replicas":0}},{"apiVersion":"apps/v1","kind":"ReplicaSet","metadata":{"annotations":{"deployment.kubernetes.io/desired-replicas":"2","deployment.kubernetes.io/max-replicas":"2","deployment.kubernetes.io/revision":"2"},"creationTimestamp":"2022-07-23T14:09:45Z","generation":3,"labels":{"app":"konnectivity-agent","component":"tunnel","pod-template-hash":"6f87dbccc6"},"name":"konnectivity-agent-6f87dbccc6","namespace":"kube-system","ownerReferences":[{"apiVersion":"apps/v1","blockOwnerDeletion":true,"controller":true,"kind":"Deployment","name":"konnectivity-agent","uid":"89eee275-352b-4565-9433-60dc075ecd40"}],"resourceVersion":"5155","uid":"387cecdc-7aff-40c9-8a02-a138771b2b79"},"spec":{"replicas":2,"selector":{"matchLabels":{"app":"konnectivity-agent","pod-template-hash":"6f87dbccc6"}},"template":{"metadata":{"annotations":{"checksum/client-cert":"bd46492bf0bb422a4a261940a97d545afee0b13872e6456ec557d59a9e010d90","checksum/service-account-key":"ac9a0ad8ebf545ad7d0c18b1279fab58134940aa694e387d61925a25cbb52497"},"creationTimestamp":null,"labels":{"app":"konnectivity-agent","component":"tunnel","pod-template-hash":"6f87dbccc6"}},"spec":{"affinity":{"nodeAffinity":{"preferredDuringSchedulingIgnoredDuringExecution":[{"preference":{"matchExpressions":[{"key":"kubernetes.azure.com/mode","operator":"In","values":["system"]}]},"weight":100}]},"podAntiAffinity":{"preferredDuringSchedulingIgnoredDuringExecution":[{"podAffinityTerm":{"labelSelector":{"matchExpressions":[{"key":"app","operator":"In","values":["konnectivity-agent"]}]},"topologyKey":"failure-domain.beta.kubernetes.io/zone"},"weight":10},{"podAffinityTerm":{"labelSelector":{"matchExpressions":[{"key":"app","operator":"In","values":["konnectivity-agent"]}]},"topologyKey":"kubernetes.io/hostname"},"weight":5}]}},"automountServiceAccountToken":false,"containers":[{"args":["--proxy-server-host=sonobuoy-test-dns-a72ecff9.hcp.canadacentral.azmk8s.io","--proxy-server-port=443","--health-server-port=8082","--keepalive-time=30s","--agent-key=/certs/client.key","--agent-cert=/certs/client.crt","--ca-cert=/certs/ca.crt","--alpn-proto=konnectivity","-v=2"],"command":["/proxy-agent"],"image":"mcr.microsoft.com/oss/kubernetes/apiserver-network-proxy/agent:v0.0.30","imagePullPolicy":"IfNotPresent","livenessProbe":{"failureThreshold":3,"httpGet":{"path":"/ready","port":8082,"scheme":"HTTP"},"initialDelaySeconds":30,"periodSeconds":60,"successThreshold":1,"timeoutSeconds":60},"name":"konnectivity-agent","readinessProbe":{"failureThreshold":3,"httpGet":{"path":"/ready","port":8082,"scheme":"HTTP"},"periodSeconds":10,"successThreshold":1,"timeoutSeconds":1},"resources":{"limits":{"cpu":"100m","memory":"128Mi"},"requests":{"cpu":"20m","memory":"20Mi"}},"terminationMessagePath":"/dev/termination-log","terminationMessagePolicy":"File","volumeMounts":[{"mountPath":"/certs","name":"certs"}]}],"dnsPolicy":"Default","nodeSelector":{"beta.kubernetes.io/os":"linux"},"priorityClassName":"system-node-critical","restartPolicy":"Always","schedulerName":"default-scheduler","securityContext":{},"serviceAccount":"konnectivity-agent","serviceAccountName":"konnectivity-agent","terminationGracePeriodSeconds":30,"tolerations":[{"key":"CriticalAddonsOnly","operator":"Exists"},{"effect":"NoExecute","key":"node.kubernetes.io/unreachable","operator":"Exists","tolerationSeconds":30},{"effect":"NoExecute","key":"node.kubernetes.io/not-ready","operator":"Exists","tolerationSeconds":30}],"volumes":[{"name":"certs","secret":{"defaultMode":420,"secretName":"konnectivity-certs"}}]}}},"status":{"availableReplicas":2,"fullyLabeledReplicas":2,"observedGeneration":3,"readyReplicas":2,"replicas":2}},{"apiVersion":"apps/v1","kind":"ReplicaSet","metadata":{"annotations":{"deployment.kubernetes.io/desired-replicas":"2","deployment.kubernetes.io/max-replicas":"3","deployment.kubernetes.io/revision":"1"},"creationTimestamp":"2022-07-23T14:09:43Z","generation":1,"labels":{"k8s-app":"metrics-server","pod-template-hash":"6d594446f4"},"name":"metrics-server-6d594446f4","namespace":"kube-system","ownerReferences":[{"apiVersion":"apps/v1","blockOwnerDeletion":true,"controller":true,"kind":"Deployment","name":"metrics-server","uid":"7f71b3d2-1d67-4935-b0fc-7af24485cf9b"}],"resourceVersion":"5815","uid":"75c77ce8-3bfb-43f9-ba5c-36343183b187"},"spec":{"replicas":2,"selector":{"matchLabels":{"k8s-app":"metrics-server","pod-template-hash":"6d594446f4"}},"template":{"metadata":{"creationTimestamp":null,"labels":{"k8s-app":"metrics-server","pod-template-hash":"6d594446f4"},"name":"metrics-server"},"spec":{"affinity":{"nodeAffinity":{"preferredDuringSchedulingIgnoredDuringExecution":[{"preference":{"matchExpressions":[{"key":"kubernetes.azure.com/mode","operator":"In","values":["system"]}]},"weight":100}],"requiredDuringSchedulingIgnoredDuringExecution":{"nodeSelectorTerms":[{"matchExpressions":[{"key":"kubernetes.azure.com/cluster","operator":"Exists"}]}]}},"podAntiAffinity":{"preferredDuringSchedulingIgnoredDuringExecution":[{"podAffinityTerm":{"labelSelector":{"matchExpressions":[{"key":"k8s-app","operator":"In","values":["metrics-server"]}]},"topologyKey":"topology.kubernetes.io/zone"},"weight":10},{"podAffinityTerm":{"labelSelector":{"matchExpressions":[{"key":"k8s-app","operator":"In","values":["metrics-server"]}]},"topologyKey":"kubernetes.io/hostname"},"weight":5}]}},"containers":[{"command":["/metrics-server","--kubelet-insecure-tls","--kubelet-preferred-address-types=InternalIP","--tls-cipher-suites=TLS_ECDHE_RSA_WITH_AES_128_GCM_SHA256,TLS_ECDHE_ECDSA_WITH_AES_128_GCM_SHA256,TLS_ECDHE_RSA_WITH_AES_256_GCM_SHA384,TLS_ECDHE_ECDSA_WITH_AES_256_GCM_SHA384","--cert-dir=/tmp","--secure-port=4443"],"image":"mcr.microsoft.com/oss/kubernetes/metrics-server:v0.5.2","imagePullPolicy":"IfNotPresent","livenessProbe":{"failureThreshold":3,"httpGet":{"path":"/livez","port":"ms-https","scheme":"HTTPS"},"initialDelaySeconds":20,"periodSeconds":10,"successThreshold":1,"timeoutSeconds":10},"name":"metrics-server","ports":[{"containerPort":4443,"name":"ms-https","protocol":"TCP"}],"readinessProbe":{"failureThreshold":3,"httpGet":{"path":"/readyz","port":"ms-https","scheme":"HTTPS"},"initialDelaySeconds":60,"periodSeconds":10,"successThreshold":1,"timeoutSeconds":10},"resources":{"limits":{"cpu":"1","memory":"4G"},"requests":{"cpu":"44m","memory":"55Mi"}},"terminationMessagePath":"/dev/termination-log","terminationMessagePolicy":"File","volumeMounts":[{"mountPath":"/tmp","name":"tmp-dir"}]}],"dnsPolicy":"ClusterFirst","nodeSelector":{"beta.kubernetes.io/os":"linux"},"priorityClassName":"system-node-critical","restartPolicy":"Always","schedulerName":"default-scheduler","securityContext":{},"serviceAccount":"metrics-server","serviceAccountName":"metrics-server","terminationGracePeriodSeconds":30,"tolerations":[{"key":"CriticalAddonsOnly","operator":"Exists"},{"effect":"NoExecute","key":"node.kubernetes.io/unreachable","operator":"Exists","tolerationSeconds":30},{"effect":"NoExecute","key":"node.kubernetes.io/not-ready","operator":"Exists","tolerationSeconds":30}],"volumes":[{"emptyDir":{},"name":"tmp-dir"}]}}},"status":{"availableReplicas":2,"fullyLabeledReplicas":2,"observedGeneration":1,"readyReplicas":2,"replicas":2}},{"apiVersion":"apps/v1","kind":"ReplicaSet","metadata":{"annotations":{"deployment.kubernetes.io/desired-replicas":"1","deployment.kubernetes.io/max-replicas":"2","deployment.kubernetes.io/revision":"1"},"creationTimestamp":"2022-07-23T14:09:43Z","generation":1,"labels":{"kubernetes.azure.com/managedby":"aks","pod-template-hash":"7674dd6b5d","rsName":"omsagent-rs"},"name":"omsagent-rs-7674dd6b5d","namespace":"kube-system","ownerReferences":[{"apiVersion":"apps/v1","blockOwnerDeletion":true,"controller":true,"kind":"Deployment","name":"omsagent-rs","uid":"46308ecd-75ea-485f-8b0f-9dd3db6ecdef"}],"resourceVersion":"5195","uid":"fd02a59c-0cea-4288-a940-d2c1748769de"},"spec":{"replicas":1,"selector":{"matchLabels":{"pod-template-hash":"7674dd6b5d","rsName":"omsagent-rs"}},"template":{"metadata":{"annotations":{"WSID":"MTNiZGRiOTctOTE1ZS00Zjg0LWJjOWMtNzRiMWE5ZmVhMmEz","agentVersion":"azure-mdsd-1.17.0","cluster-autoscaler.kubernetes.io/safe-to-evict":"true","dockerProviderVersion":"18.0.1-0","kubernetes.azure.com/no-http-proxy-vars":"true","schema-versions":"v1"},"creationTimestamp":null,"labels":{"kubernetes.azure.com/managedby":"aks","pod-template-hash":"7674dd6b5d","rsName":"omsagent-rs"}},"spec":{"affinity":{"nodeAffinity":{"preferredDuringSchedulingIgnoredDuringExecution":[{"preference":{"matchExpressions":[{"key":"kubernetes.azure.com/mode","operator":"In","values":["system"]}]},"weight":100},{"preference":{"matchExpressions":[{"key":"storageprofile","operator":"NotIn","values":["managed"]}]},"weight":1}],"requiredDuringSchedulingIgnoredDuringExecution":{"nodeSelectorTerms":[{"matchExpressions":[{"key":"beta.kubernetes.io/os","operator":"In","values":["linux"]},{"key":"kubernetes.io/role","operator":"In","values":["agent"]},{"key":"kubernetes.azure.com/cluster","operator":"Exists"},{"key":"type","operator":"NotIn","values":["virtual-kubelet"]}]}]}}},"containers":[{"env":[{"name":"NODE_IP","valueFrom":{"fieldRef":{"apiVersion":"v1","fieldPath":"status.hostIP"}}},{"name":"AKS_CLUSTER_NAME","value":"sonobuoy-test"},{"name":"AKS_RESOURCE_ID","value":"/subscriptions/ce859648-30e1-4135-9d0f-8358aebfe789/resourceGroups/sonobuoy-te_group/providers/Microsoft.ContainerService/managedClusters/sonobuoy-test"},{"name":"AKS_NODE_RESOURCE_GROUP","value":"MC_sonobuoy-te_group_sonobuoy-test_canadacentral"},{"name":"AKS_REGION","value":"canadacentral"},{"name":"CONTROLLER_TYPE","value":"ReplicaSet"},{"name":"USER_ASSIGNED_IDENTITY_CLIENT_ID","value":"a02c4905-04be-41ca-85b6-32d86766e758"},{"name":"NUM_OF_FLUENTD_WORKERS","valueFrom":{"resourceFieldRef":{"containerName":"omsagent","divisor":"0","resource":"limits.cpu"}}},{"name":"SIDECAR_SCRAPING_ENABLED","value":"true"},{"name":"USING_AAD_MSI_AUTH","value":"false"}],"image":"mcr.microsoft.com/azuremonitor/containerinsights/ciprod:ciprod06272022","imagePullPolicy":"IfNotPresent","livenessProbe":{"exec":{"command":["/bin/bash","-c","/opt/livenessprobe.sh"]},"failureThreshold":3,"initialDelaySeconds":60,"periodSeconds":60,"successThreshold":1,"timeoutSeconds":15},"name":"omsagent","ports":[{"containerPort":25225,"protocol":"TCP"},{"containerPort":25224,"protocol":"UDP"},{"containerPort":25227,"name":"in-rs-tcp","protocol":"TCP"}],"resources":{"limits":{"cpu":"1","memory":"1Gi"},"requests":{"cpu":"150m","memory":"250Mi"}},"securityContext":{"privileged":true},"terminationMessagePath":"/dev/termination-log","terminationMessagePolicy":"File","volumeMounts":[{"mountPath":"/var/run/host","name":"docker-sock"},{"mountPath":"/var/log","name":"host-log"},{"mountPath":"/etc/kubernetes/host","name":"azure-json-path"},{"mountPath":"/etc/omsagent-secret","name":"omsagent-secret","readOnly":true},{"mountPath":"/etc/config","name":"omsagent-rs-config"},{"mountPath":"/etc/config/settings","name":"settings-vol-config","readOnly":true},{"mountPath":"/etc/config/settings/adx","name":"omsagent-adx-secret","readOnly":true},{"mountPath":"/etc/config/osm-settings","name":"osm-settings-vol-config","readOnly":true}]}],"dnsPolicy":"ClusterFirst","priorityClassName":"system-node-critical","restartPolicy":"Always","schedulerName":"default-scheduler","securityContext":{},"serviceAccount":"omsagent","serviceAccountName":"omsagent","terminationGracePeriodSeconds":30,"tolerations":[{"key":"CriticalAddonsOnly","operator":"Exists"}],"volumes":[{"hostPath":{"path":"/var/run","type":""},"name":"docker-sock"},{"hostPath":{"path":"/etc/hostname","type":""},"name":"container-hostname"},{"hostPath":{"path":"/var/log","type":""},"name":"host-log"},{"hostPath":{"path":"/etc/kubernetes","type":""},"name":"azure-json-path"},{"name":"omsagent-secret","secret":{"defaultMode":420,"secretName":"omsagent-secret"}},{"configMap":{"defaultMode":420,"name":"omsagent-rs-config"},"name":"omsagent-rs-config"},{"configMap":{"defaultMode":420,"name":"container-azm-ms-agentconfig","optional":true},"name":"settings-vol-config"},{"name":"omsagent-adx-secret","secret":{"defaultMode":420,"optional":true,"secretName":"omsagent-adx-secret"}},{"configMap":{"defaultMode":420,"name":"container-azm-ms-osmconfig","optional":true},"name":"osm-settings-vol-config"}]}}},"status":{"availableReplicas":1,"fullyLabeledReplicas":1,"observedGeneration":1,"readyReplicas":1,"replicas":1}}],"kind":"ReplicaSetList","metadata":{"resourceVersion":"15220"}}
