{"apiVersion":"v1","items":[{"apiVersion":"v1","kind":"Pod","metadata":{"creationTimestamp":"2022-07-23T14:10:54Z","generateName":"azure-ip-masq-agent-","labels":{"controller-revision-hash":"7d65bc8db6","k8s-app":"azure-ip-masq-agent","pod-template-generation":"1","tier":"node"},"name":"azure-ip-masq-agent-rbvlj","namespace":"kube-system","ownerReferences":[{"apiVersion":"apps/v1","blockOwnerDeletion":true,"controller":true,"kind":"DaemonSet","name":"azure-ip-masq-agent","uid":"caa0f381-f4a7-4f99-92d3-982ecac3e610"}],"resourceVersion":"969","uid":"23ebafa7-5cd6-4bc5-8078-dd529a205a12"},"spec":{"affinity":{"nodeAffinity":{"requiredDuringSchedulingIgnoredDuringExecution":{"nodeSelectorTerms":[{"matchFields":[{"key":"metadata.name","operator":"In","values":["aks-agentpool-16430811-vmss000002"]}]}]}}},"containers":[{"args":["--v=2","--resync-interval=60"],"env":[{"name":"KUBERNETES_PORT_443_TCP_ADDR","value":"sonobuoy-test-dns-a72ecff9.hcp.canadacentral.azmk8s.io"},{"name":"KUBERNETES_PORT","value":"tcp://sonobuoy-test-dns-a72ecff9.hcp.canadacentral.azmk8s.io:443"},{"name":"KUBERNETES_PORT_443_TCP","value":"tcp://sonobuoy-test-dns-a72ecff9.hcp.canadacentral.azmk8s.io:443"},{"name":"KUBERNETES_SERVICE_HOST","value":"sonobuoy-test-dns-a72ecff9.hcp.canadacentral.azmk8s.io"}],"image":"mcr.microsoft.com/aks/ip-masq-agent-v2:v0.1.3","imagePullPolicy":"IfNotPresent","name":"azure-ip-masq-agent","resources":{"limits":{"cpu":"500m","memory":"250Mi"},"requests":{"cpu":"100m","memory":"50Mi"}},"securityContext":{"capabilities":{"add":["NET_ADMIN","NET_RAW"]}},"terminationMessagePath":"/dev/termination-log","terminationMessagePolicy":"File","volumeMounts":[{"mountPath":"/etc/config","name":"azure-ip-masq-agent-config-volume"},{"mountPath":"/run/xtables.lock","name":"iptableslock"},{"mountPath":"/var/run/secrets/kubernetes.io/serviceaccount","name":"kube-api-access-tdpc8","readOnly":true}]}],"dnsPolicy":"ClusterFirst","enableServiceLinks":true,"hostNetwork":true,"nodeName":"aks-agentpool-16430811-vmss000002","preemptionPolicy":"PreemptLowerPriority","priority":2000001000,"priorityClassName":"system-node-critical","restartPolicy":"Always","schedulerName":"default-scheduler","securityContext":{},"serviceAccount":"default","serviceAccountName":"default","terminationGracePeriodSeconds":30,"tolerations":[{"key":"CriticalAddonsOnly","operator":"Exists"},{"effect":"NoExecute","operator":"Exists"},{"effect":"NoSchedule","operator":"Exists"}],"volumes":[{"name":"azure-ip-masq-agent-config-volume","projected":{"defaultMode":420,"sources":[{"configMap":{"items":[{"key":"ip-masq-agent","mode":444,"path":"ip-masq-agent"}],"name":"azure-ip-masq-agent-config","optional":true}},{"configMap":{"items":[{"key":"ip-masq-agent-reconciled","mode":444,"path":"ip-masq-agent-reconciled"}],"name":"azure-ip-masq-agent-config-reconciled","optional":true}}]}},{"hostPath":{"path":"/run/xtables.lock","type":"FileOrCreate"},"name":"iptableslock"},{"name":"kube-api-access-tdpc8","projected":{"defaultMode":420,"sources":[{"serviceAccountToken":{"expirationSeconds":3607,"path":"token"}},{"configMap":{"items":[{"key":"ca.crt","path":"ca.crt"}],"name":"kube-root-ca.crt"}},{"downwardAPI":{"items":[{"fieldRef":{"apiVersion":"v1","fieldPath":"metadata.namespace"},"path":"namespace"}]}}]}}]},"status":{"conditions":[{"lastProbeTime":null,"lastTransitionTime":"2022-07-23T14:10:55Z","status":"True","type":"Initialized"},{"lastProbeTime":null,"lastTransitionTime":"2022-07-23T14:10:58Z","status":"True","type":"Ready"},{"lastProbeTime":null,"lastTransitionTime":"2022-07-23T14:10:58Z","status":"True","type":"ContainersReady"},{"lastProbeTime":null,"lastTransitionTime":"2022-07-23T14:10:54Z","status":"True","type":"PodScheduled"}],"containerStatuses":[{"containerID":"containerd://5faf009455de1a10b3280e4f757156a399b1a9f5ac58f8844897113efb3c52f3","image":"mcr.microsoft.com/aks/ip-masq-agent-v2:v0.1.3","imageID":"sha256:6c3dd649baa57279888709fe61100969ebd302a5e9f41e8678046fa0a0266c3e","lastState":{},"name":"azure-ip-masq-agent","ready":true,"restartCount":0,"started":true,"state":{"running":{"startedAt":"2022-07-23T14:10:58Z"}}}],"hostIP":"10.224.0.6","phase":"Running","podIP":"10.224.0.6","podIPs":[{"ip":"10.224.0.6"}],"qosClass":"Burstable","startTime":"2022-07-23T14:10:55Z"}},{"apiVersion":"v1","kind":"Pod","metadata":{"annotations":{"cluster-autoscaler.kubernetes.io/daemonset-pod":"true"},"creationTimestamp":"2022-07-23T14:10:54Z","generateName":"cloud-node-manager-","labels":{"controller-revision-hash":"7b48f5ffb6","k8s-app":"cloud-node-manager","pod-template-generation":"1"},"name":"cloud-node-manager-8fw89","namespace":"kube-system","ownerReferences":[{"apiVersion":"apps/v1","blockOwnerDeletion":true,"controller":true,"kind":"DaemonSet","name":"cloud-node-manager","uid":"7f562242-bcb3-41da-9341-5eca67960c8e"}],"resourceVersion":"979","uid":"f3316ea2-1f4b-4909-8370-6ea560206aca"},"spec":{"affinity":{"nodeAffinity":{"requiredDuringSchedulingIgnoredDuringExecution":{"nodeSelectorTerms":[{"matchFields":[{"key":"metadata.name","operator":"In","values":["aks-agentpool-16430811-vmss000002"]}]}]}}},"containers":[{"command":["cloud-node-manager","--node-name=$(NODE_NAME)","--wait-routes"],"env":[{"name":"NODE_NAME","valueFrom":{"fieldRef":{"apiVersion":"v1","fieldPath":"spec.nodeName"}}},{"name":"KUBERNETES_PORT_443_TCP_ADDR","value":"sonobuoy-test-dns-a72ecff9.hcp.canadacentral.azmk8s.io"},{"name":"KUBERNETES_PORT","value":"tcp://sonobuoy-test-dns-a72ecff9.hcp.canadacentral.azmk8s.io:443"},{"name":"KUBERNETES_PORT_443_TCP","value":"tcp://sonobuoy-test-dns-a72ecff9.hcp.canadacentral.azmk8s.io:443"},{"name":"KUBERNETES_SERVICE_HOST","value":"sonobuoy-test-dns-a72ecff9.hcp.canadacentral.azmk8s.io"}],"image":"mcr.microsoft.com/oss/kubernetes/azure-cloud-node-manager:v1.23.11","imagePullPolicy":"IfNotPresent","name":"cloud-node-manager","resources":{"limits":{"cpu":"2","memory":"512Mi"},"requests":{"cpu":"50m","memory":"50Mi"}},"terminationMessagePath":"/dev/termination-log","terminationMessagePolicy":"File","volumeMounts":[{"mountPath":"/var/run/secrets/kubernetes.io/serviceaccount","name":"kube-api-access-95fwk","readOnly":true}]}],"dnsPolicy":"ClusterFirst","enableServiceLinks":true,"hostNetwork":true,"nodeName":"aks-agentpool-16430811-vmss000002","preemptionPolicy":"PreemptLowerPriority","priority":2000001000,"priorityClassName":"system-node-critical","restartPolicy":"Always","schedulerName":"default-scheduler","securityContext":{},"serviceAccount":"cloud-node-manager","serviceAccountName":"cloud-node-manager","terminationGracePeriodSeconds":30,"tolerations":[{"key":"CriticalAddonsOnly","operator":"Exists"},{"effect":"NoExecute","operator":"Exists"},{"effect":"NoSchedule","operator":"Exists"}],"volumes":[{"name":"kube-api-access-95fwk","projected":{"defaultMode":420,"sources":[{"serviceAccountToken":{"expirationSeconds":3607,"path":"token"}},{"configMap":{"items":[{"key":"ca.crt","path":"ca.crt"}],"name":"kube-root-ca.crt"}},{"downwardAPI":{"items":[{"fieldRef":{"apiVersion":"v1","fieldPath":"metadata.namespace"},"path":"namespace"}]}}]}}]},"status":{"conditions":[{"lastProbeTime":null,"lastTransitionTime":"2022-07-23T14:10:55Z","status":"True","type":"Initialized"},{"lastProbeTime":null,"lastTransitionTime":"2022-07-23T14:10:58Z","status":"True","type":"Ready"},{"lastProbeTime":null,"lastTransitionTime":"2022-07-23T14:10:58Z","status":"True","type":"ContainersReady"},{"lastProbeTime":null,"lastTransitionTime":"2022-07-23T14:10:54Z","status":"True","type":"PodScheduled"}],"containerStatuses":[{"containerID":"containerd://81ed38cd0f0c3c84c82920e70ebd497a7ee9217e98fce18ba0904aaa0bdf6614","image":"mcr.microsoft.com/oss/kubernetes/azure-cloud-node-manager:v1.23.11","imageID":"sha256:a2e084306a5d63e8fa62ce85189087e773e1bfe2208a190ede77bf7ee45b23c6","lastState":{},"name":"cloud-node-manager","ready":true,"restartCount":0,"started":true,"state":{"running":{"startedAt":"2022-07-23T14:10:58Z"}}}],"hostIP":"10.224.0.6","phase":"Running","podIP":"10.224.0.6","podIPs":[{"ip":"10.224.0.6"}],"qosClass":"Burstable","startTime":"2022-07-23T14:10:55Z"}},{"apiVersion":"v1","kind":"Pod","metadata":{"annotations":{"prometheus.io/port":"9153"},"creationTimestamp":"2022-07-23T14:26:48Z","generateName":"coredns-87688dc49-","labels":{"k8s-app":"kube-dns","kubernetes.io/cluster-service":"true","pod-template-hash":"87688dc49","version":"v20"},"name":"coredns-87688dc49-kfvjc","namespace":"kube-system","ownerReferences":[{"apiVersion":"apps/v1","blockOwnerDeletion":true,"controller":true,"kind":"ReplicaSet","name":"coredns-87688dc49","uid":"1d431369-2c41-41fd-9a78-6f26d2f445cf"}],"resourceVersion":"5173","uid":"91cefc9c-7e00-4363-8133-93a6ccde9b2a"},"spec":{"affinity":{"nodeAffinity":{"preferredDuringSchedulingIgnoredDuringExecution":[{"preference":{"matchExpressions":[{"key":"kubernetes.azure.com/mode","operator":"In","values":["system"]}]},"weight":100}]},"podAntiAffinity":{"preferredDuringSchedulingIgnoredDuringExecution":[{"podAffinityTerm":{"labelSelector":{"matchExpressions":[{"key":"k8s-app","operator":"In","values":["kube-dns"]}]},"topologyKey":"failure-domain.beta.kubernetes.io/zone"},"weight":10},{"podAffinityTerm":{"labelSelector":{"matchExpressions":[{"key":"k8s-app","operator":"In","values":["kube-dns"]}]},"topologyKey":"kubernetes.io/hostname"},"weight":5}]}},"containers":[{"args":["-conf","/etc/coredns/Corefile"],"env":[{"name":"KUBERNETES_PORT_443_TCP_ADDR","value":"sonobuoy-test-dns-a72ecff9.hcp.canadacentral.azmk8s.io"},{"name":"KUBERNETES_PORT","value":"tcp://sonobuoy-test-dns-a72ecff9.hcp.canadacentral.azmk8s.io:443"},{"name":"KUBERNETES_PORT_443_TCP","value":"tcp://sonobuoy-test-dns-a72ecff9.hcp.canadacentral.azmk8s.io:443"},{"name":"KUBERNETES_SERVICE_HOST","value":"sonobuoy-test-dns-a72ecff9.hcp.canadacentral.azmk8s.io"}],"image":"mcr.microsoft.com/oss/kubernetes/coredns:v1.8.7","imagePullPolicy":"IfNotPresent","livenessProbe":{"failureThreshold":5,"httpGet":{"path":"/health","port":8080,"scheme":"HTTP"},"initialDelaySeconds":60,"periodSeconds":10,"successThreshold":1,"timeoutSeconds":5},"name":"coredns","ports":[{"containerPort":53,"name":"dns","protocol":"UDP"},{"containerPort":53,"name":"dns-tcp","protocol":"TCP"},{"containerPort":9153,"name":"metrics","protocol":"TCP"}],"readinessProbe":{"failureThreshold":3,"httpGet":{"path":"/ready","port":8181,"scheme":"HTTP"},"periodSeconds":10,"successThreshold":1,"timeoutSeconds":1},"resources":{"limits":{"cpu":"3","memory":"500Mi"},"requests":{"cpu":"100m","memory":"70Mi"}},"securityContext":{"allowPrivilegeEscalation":false,"capabilities":{"add":["NET_BIND_SERVICE"],"drop":["all"]},"procMount":"Default","readOnlyRootFilesystem":true},"terminationMessagePath":"/dev/termination-log","terminationMessagePolicy":"File","volumeMounts":[{"mountPath":"/etc/coredns","name":"config-volume","readOnly":true},{"mountPath":"/etc/coredns/custom","name":"custom-config-volume","readOnly":true},{"mountPath":"/tmp","name":"tmp"},{"mountPath":"/var/run/secrets/kubernetes.io/serviceaccount","name":"kube-api-access-scw28","readOnly":true}]}],"dnsPolicy":"Default","enableServiceLinks":true,"nodeName":"aks-agentpool-16430811-vmss000002","nodeSelector":{"beta.kubernetes.io/os":"linux"},"preemptionPolicy":"PreemptLowerPriority","priority":2000001000,"priorityClassName":"system-node-critical","restartPolicy":"Always","schedulerName":"default-scheduler","securityContext":{},"serviceAccount":"coredns","serviceAccountName":"coredns","terminationGracePeriodSeconds":30,"tolerations":[{"effect":"NoSchedule","key":"node-role.kubernetes.io/master"},{"key":"CriticalAddonsOnly","operator":"Exists"},{"effect":"NoExecute","key":"node.kubernetes.io/unreachable","operator":"Exists","tolerationSeconds":30},{"effect":"NoExecute","key":"node.kubernetes.io/not-ready","operator":"Exists","tolerationSeconds":30},{"effect":"NoSchedule","key":"node.kubernetes.io/memory-pressure","operator":"Exists"}],"volumes":[{"configMap":{"defaultMode":420,"items":[{"key":"Corefile","path":"Corefile"}],"name":"coredns"},"name":"config-volume"},{"configMap":{"defaultMode":420,"name":"coredns-custom","optional":true},"name":"custom-config-volume"},{"emptyDir":{},"name":"tmp"},{"name":"kube-api-access-scw28","projected":{"defaultMode":420,"sources":[{"serviceAccountToken":{"expirationSeconds":3607,"path":"token"}},{"configMap":{"items":[{"key":"ca.crt","path":"ca.crt"}],"name":"kube-root-ca.crt"}},{"downwardAPI":{"items":[{"fieldRef":{"apiVersion":"v1","fieldPath":"metadata.namespace"},"path":"namespace"}]}}]}}]},"status":{"conditions":[{"lastProbeTime":null,"lastTransitionTime":"2022-07-23T14:26:48Z","status":"True","type":"Initialized"},{"lastProbeTime":null,"lastTransitionTime":"2022-07-23T14:26:49Z","status":"True","type":"Ready"},{"lastProbeTime":null,"lastTransitionTime":"2022-07-23T14:26:49Z","status":"True","type":"ContainersReady"},{"lastProbeTime":null,"lastTransitionTime":"2022-07-23T14:26:48Z","status":"True","type":"PodScheduled"}],"containerStatuses":[{"containerID":"containerd://dd78d9d34a00e34f52626e663655d6cc98462d21df59f50f9bc4b8f5ec6b372a","image":"mcr.microsoft.com/oss/kubernetes/coredns:v1.8.7","imageID":"sha256:6a16df5be865c0d90b77b498674fad302921917cad52f509386cd322fbd3ccef","lastState":{},"name":"coredns","ready":true,"restartCount":0,"started":true,"state":{"running":{"startedAt":"2022-07-23T14:26:49Z"}}}],"hostIP":"10.224.0.6","phase":"Running","podIP":"10.244.1.7","podIPs":[{"ip":"10.244.1.7"}],"qosClass":"Burstable","startTime":"2022-07-23T14:26:48Z"}},{"apiVersion":"v1","kind":"Pod","metadata":{"annotations":{"prometheus.io/port":"9153"},"creationTimestamp":"2022-07-23T14:11:41Z","generateName":"coredns-87688dc49-","labels":{"k8s-app":"kube-dns","kubernetes.io/cluster-service":"true","pod-template-hash":"87688dc49","version":"v20"},"name":"coredns-87688dc49-qxmgb","namespace":"kube-system","ownerReferences":[{"apiVersion":"apps/v1","blockOwnerDeletion":true,"controller":true,"kind":"ReplicaSet","name":"coredns-87688dc49","uid":"1d431369-2c41-41fd-9a78-6f26d2f445cf"}],"resourceVersion":"1365","uid":"a302b0be-dadf-4ab0-9c4b-3740d3347c06"},"spec":{"affinity":{"nodeAffinity":{"preferredDuringSchedulingIgnoredDuringExecution":[{"preference":{"matchExpressions":[{"key":"kubernetes.azure.com/mode","operator":"In","values":["system"]}]},"weight":100}]},"podAntiAffinity":{"preferredDuringSchedulingIgnoredDuringExecution":[{"podAffinityTerm":{"labelSelector":{"matchExpressions":[{"key":"k8s-app","operator":"In","values":["kube-dns"]}]},"topologyKey":"failure-domain.beta.kubernetes.io/zone"},"weight":10},{"podAffinityTerm":{"labelSelector":{"matchExpressions":[{"key":"k8s-app","operator":"In","values":["kube-dns"]}]},"topologyKey":"kubernetes.io/hostname"},"weight":5}]}},"containers":[{"args":["-conf","/etc/coredns/Corefile"],"env":[{"name":"KUBERNETES_PORT_443_TCP_ADDR","value":"sonobuoy-test-dns-a72ecff9.hcp.canadacentral.azmk8s.io"},{"name":"KUBERNETES_PORT","value":"tcp://sonobuoy-test-dns-a72ecff9.hcp.canadacentral.azmk8s.io:443"},{"name":"KUBERNETES_PORT_443_TCP","value":"tcp://sonobuoy-test-dns-a72ecff9.hcp.canadacentral.azmk8s.io:443"},{"name":"KUBERNETES_SERVICE_HOST","value":"sonobuoy-test-dns-a72ecff9.hcp.canadacentral.azmk8s.io"}],"image":"mcr.microsoft.com/oss/kubernetes/coredns:v1.8.7","imagePullPolicy":"IfNotPresent","livenessProbe":{"failureThreshold":5,"httpGet":{"path":"/health","port":8080,"scheme":"HTTP"},"initialDelaySeconds":60,"periodSeconds":10,"successThreshold":1,"timeoutSeconds":5},"name":"coredns","ports":[{"containerPort":53,"name":"dns","protocol":"UDP"},{"containerPort":53,"name":"dns-tcp","protocol":"TCP"},{"containerPort":9153,"name":"metrics","protocol":"TCP"}],"readinessProbe":{"failureThreshold":3,"httpGet":{"path":"/ready","port":8181,"scheme":"HTTP"},"periodSeconds":10,"successThreshold":1,"timeoutSeconds":1},"resources":{"limits":{"cpu":"3","memory":"500Mi"},"requests":{"cpu":"100m","memory":"70Mi"}},"securityContext":{"allowPrivilegeEscalation":false,"capabilities":{"add":["NET_BIND_SERVICE"],"drop":["all"]},"procMount":"Default","readOnlyRootFilesystem":true},"terminationMessagePath":"/dev/termination-log","terminationMessagePolicy":"File","volumeMounts":[{"mountPath":"/etc/coredns","name":"config-volume","readOnly":true},{"mountPath":"/etc/coredns/custom","name":"custom-config-volume","readOnly":true},{"mountPath":"/tmp","name":"tmp"},{"mountPath":"/var/run/secrets/kubernetes.io/serviceaccount","name":"kube-api-access-h9z9n","readOnly":true}]}],"dnsPolicy":"Default","enableServiceLinks":true,"nodeName":"aks-agentpool-16430811-vmss000002","nodeSelector":{"beta.kubernetes.io/os":"linux"},"preemptionPolicy":"PreemptLowerPriority","priority":2000001000,"priorityClassName":"system-node-critical","restartPolicy":"Always","schedulerName":"default-scheduler","securityContext":{},"serviceAccount":"coredns","serviceAccountName":"coredns","terminationGracePeriodSeconds":30,"tolerations":[{"effect":"NoSchedule","key":"node-role.kubernetes.io/master"},{"key":"CriticalAddonsOnly","operator":"Exists"},{"effect":"NoExecute","key":"node.kubernetes.io/unreachable","operator":"Exists","tolerationSeconds":30},{"effect":"NoExecute","key":"node.kubernetes.io/not-ready","operator":"Exists","tolerationSeconds":30},{"effect":"NoSchedule","key":"node.kubernetes.io/memory-pressure","operator":"Exists"}],"volumes":[{"configMap":{"defaultMode":420,"items":[{"key":"Corefile","path":"Corefile"}],"name":"coredns"},"name":"config-volume"},{"configMap":{"defaultMode":420,"name":"coredns-custom","optional":true},"name":"custom-config-volume"},{"emptyDir":{},"name":"tmp"},{"name":"kube-api-access-h9z9n","projected":{"defaultMode":420,"sources":[{"serviceAccountToken":{"expirationSeconds":3607,"path":"token"}},{"configMap":{"items":[{"key":"ca.crt","path":"ca.crt"}],"name":"kube-root-ca.crt"}},{"downwardAPI":{"items":[{"fieldRef":{"apiVersion":"v1","fieldPath":"metadata.namespace"},"path":"namespace"}]}}]}}]},"status":{"conditions":[{"lastProbeTime":null,"lastTransitionTime":"2022-07-23T14:11:41Z","status":"True","type":"Initialized"},{"lastProbeTime":null,"lastTransitionTime":"2022-07-23T14:11:51Z","status":"True","type":"Ready"},{"lastProbeTime":null,"lastTransitionTime":"2022-07-23T14:11:51Z","status":"True","type":"ContainersReady"},{"lastProbeTime":null,"lastTransitionTime":"2022-07-23T14:11:41Z","status":"True","type":"PodScheduled"}],"containerStatuses":[{"containerID":"containerd://59b89cf1b67abbbe54d7e3c4a5fda75c067d3d57388e8661c6de4f15b4715a27","image":"mcr.microsoft.com/oss/kubernetes/coredns:v1.8.7","imageID":"sha256:6a16df5be865c0d90b77b498674fad302921917cad52f509386cd322fbd3ccef","lastState":{},"name":"coredns","ready":true,"restartCount":0,"started":true,"state":{"running":{"startedAt":"2022-07-23T14:11:41Z"}}}],"hostIP":"10.224.0.6","phase":"Running","podIP":"10.244.1.4","podIPs":[{"ip":"10.244.1.4"}],"qosClass":"Burstable","startTime":"2022-07-23T14:11:41Z"}},{"apiVersion":"v1","kind":"Pod","metadata":{"annotations":{"cluster-autoscaler.kubernetes.io/safe-to-evict":"true","seccomp.security.alpha.kubernetes.io/pod":"runtime/default"},"creationTimestamp":"2022-07-23T14:26:48Z","generateName":"coredns-autoscaler-84bdbbc855-","labels":{"k8s-app":"coredns-autoscaler","pod-template-hash":"84bdbbc855"},"name":"coredns-autoscaler-84bdbbc855-qqqjg","namespace":"kube-system","ownerReferences":[{"apiVersion":"apps/v1","blockOwnerDeletion":true,"controller":true,"kind":"ReplicaSet","name":"coredns-autoscaler-84bdbbc855","uid":"3b73fb94-baa3-4712-a65a-af497965a758"}],"resourceVersion":"5188","uid":"4f9a5bdf-d2b8-44c5-8b4d-d2c305cff66d"},"spec":{"affinity":{"nodeAffinity":{"preferredDuringSchedulingIgnoredDuringExecution":[{"preference":{"matchExpressions":[{"key":"kubernetes.azure.com/mode","operator":"In","values":["system"]}]},"weight":100}]}},"containers":[{"command":["/cluster-proportional-autoscaler","--namespace=kube-system","--configmap=coredns-autoscaler","--target=deployment/coredns","--default-params={\"ladder\":{\"coresToReplicas\":[[1,2],[512,3],[1024,4],[2048,5]],\"nodesToReplicas\":[[1,2],[8,3],[16,4],[32,5]]}}","--logtostderr=true","--v=2"],"env":[{"name":"KUBERNETES_PORT_443_TCP_ADDR","value":"sonobuoy-test-dns-a72ecff9.hcp.canadacentral.azmk8s.io"},{"name":"KUBERNETES_PORT","value":"tcp://sonobuoy-test-dns-a72ecff9.hcp.canadacentral.azmk8s.io:443"},{"name":"KUBERNETES_PORT_443_TCP","value":"tcp://sonobuoy-test-dns-a72ecff9.hcp.canadacentral.azmk8s.io:443"},{"name":"KUBERNETES_SERVICE_HOST","value":"sonobuoy-test-dns-a72ecff9.hcp.canadacentral.azmk8s.io"}],"image":"mcr.microsoft.com/oss/kubernetes/autoscaler/cluster-proportional-autoscaler:1.8.5","imagePullPolicy":"IfNotPresent","livenessProbe":{"failureThreshold":3,"httpGet":{"path":"/last-poll","port":8080,"scheme":"HTTP"},"initialDelaySeconds":10,"periodSeconds":10,"successThreshold":1,"timeoutSeconds":1},"name":"autoscaler","resources":{"limits":{"cpu":"200m","memory":"1G"},"requests":{"cpu":"20m","memory":"10Mi"}},"terminationMessagePath":"/dev/termination-log","terminationMessagePolicy":"File","volumeMounts":[{"mountPath":"/var/run/secrets/kubernetes.io/serviceaccount","name":"kube-api-access-sm7wt","readOnly":true}]}],"dnsPolicy":"Default","enableServiceLinks":true,"nodeName":"aks-agentpool-16430811-vmss000002","nodeSelector":{"beta.kubernetes.io/os":"linux"},"preemptionPolicy":"PreemptLowerPriority","priority":2000001000,"priorityClassName":"system-node-critical","restartPolicy":"Always","schedulerName":"default-scheduler","securityContext":{"seccompProfile":{"type":"RuntimeDefault"}},"serviceAccount":"coredns-autoscaler","serviceAccountName":"coredns-autoscaler","terminationGracePeriodSeconds":30,"tolerations":[{"key":"CriticalAddonsOnly","operator":"Exists"},{"effect":"NoExecute","key":"node.kubernetes.io/unreachable","operator":"Exists","tolerationSeconds":30},{"effect":"NoExecute","key":"node.kubernetes.io/not-ready","operator":"Exists","tolerationSeconds":30},{"effect":"NoSchedule","key":"node.kubernetes.io/memory-pressure","operator":"Exists"}],"volumes":[{"name":"kube-api-access-sm7wt","projected":{"defaultMode":420,"sources":[{"serviceAccountToken":{"expirationSeconds":3607,"path":"token"}},{"configMap":{"items":[{"key":"ca.crt","path":"ca.crt"}],"name":"kube-root-ca.crt"}},{"downwardAPI":{"items":[{"fieldRef":{"apiVersion":"v1","fieldPath":"metadata.namespace"},"path":"namespace"}]}}]}}]},"status":{"conditions":[{"lastProbeTime":null,"lastTransitionTime":"2022-07-23T14:26:48Z","status":"True","type":"Initialized"},{"lastProbeTime":null,"lastTransitionTime":"2022-07-23T14:26:50Z","status":"True","type":"Ready"},{"lastProbeTime":null,"lastTransitionTime":"2022-07-23T14:26:50Z","status":"True","type":"ContainersReady"},{"lastProbeTime":null,"lastTransitionTime":"2022-07-23T14:26:48Z","status":"True","type":"PodScheduled"}],"containerStatuses":[{"containerID":"containerd://a5f10494bc6c318f98a347adeecb7ac00bb846e772ec6ed39c1a479198d1731e","image":"mcr.microsoft.com/oss/kubernetes/autoscaler/cluster-proportional-autoscaler:1.8.5","imageID":"sha256:67f622f206c864b3e5404c451ffc3febae94ed781fbd0d3c77369963e42244f9","lastState":{},"name":"autoscaler","ready":true,"restartCount":0,"started":true,"state":{"running":{"startedAt":"2022-07-23T14:26:50Z"}}}],"hostIP":"10.224.0.6","phase":"Running","podIP":"10.244.1.9","podIPs":[{"ip":"10.244.1.9"}],"qosClass":"Burstable","startTime":"2022-07-23T14:26:48Z"}},{"apiVersion":"v1","kind":"Pod","metadata":{"creationTimestamp":"2022-07-23T14:10:54Z","generateName":"csi-azuredisk-node-","labels":{"app":"csi-azuredisk-node","controller-revision-hash":"575c7557f8","pod-template-generation":"1"},"name":"csi-azuredisk-node-vljzc","namespace":"kube-system","ownerReferences":[{"apiVersion":"apps/v1","blockOwnerDeletion":true,"controller":true,"kind":"DaemonSet","name":"csi-azuredisk-node","uid":"2e676b72-3bc5-445f-8f6f-8c1c20820953"}],"resourceVersion":"988","uid":"566f0ac1-1176-4332-8f84-0eb772ee6031"},"spec":{"affinity":{"nodeAffinity":{"requiredDuringSchedulingIgnoredDuringExecution":{"nodeSelectorTerms":[{"matchFields":[{"key":"metadata.name","operator":"In","values":["aks-agentpool-16430811-vmss000002"]}]}]}}},"containers":[{"args":["--csi-address=/csi/csi.sock","--probe-timeout=3s","--health-port=29603","--v=2"],"env":[{"name":"KUBERNETES_PORT_443_TCP_ADDR","value":"sonobuoy-test-dns-a72ecff9.hcp.canadacentral.azmk8s.io"},{"name":"KUBERNETES_PORT","value":"tcp://sonobuoy-test-dns-a72ecff9.hcp.canadacentral.azmk8s.io:443"},{"name":"KUBERNETES_PORT_443_TCP","value":"tcp://sonobuoy-test-dns-a72ecff9.hcp.canadacentral.azmk8s.io:443"},{"name":"KUBERNETES_SERVICE_HOST","value":"sonobuoy-test-dns-a72ecff9.hcp.canadacentral.azmk8s.io"}],"image":"mcr.microsoft.com/oss/kubernetes-csi/livenessprobe:v2.6.0","imagePullPolicy":"IfNotPresent","name":"liveness-probe","resources":{"limits":{"memory":"100Mi"},"requests":{"cpu":"10m","memory":"20Mi"}},"terminationMessagePath":"/dev/termination-log","terminationMessagePolicy":"File","volumeMounts":[{"mountPath":"/csi","name":"socket-dir"},{"mountPath":"/var/run/secrets/kubernetes.io/serviceaccount","name":"kube-api-access-w2ddh","readOnly":true}]},{"args":["--csi-address=$(ADDRESS)","--kubelet-registration-path=$(DRIVER_REG_SOCK_PATH)","--v=2"],"env":[{"name":"ADDRESS","value":"/csi/csi.sock"},{"name":"DRIVER_REG_SOCK_PATH","value":"/var/lib/kubelet/plugins/disk.csi.azure.com/csi.sock"},{"name":"KUBERNETES_PORT_443_TCP_ADDR","value":"sonobuoy-test-dns-a72ecff9.hcp.canadacentral.azmk8s.io"},{"name":"KUBERNETES_PORT","value":"tcp://sonobuoy-test-dns-a72ecff9.hcp.canadacentral.azmk8s.io:443"},{"name":"KUBERNETES_PORT_443_TCP","value":"tcp://sonobuoy-test-dns-a72ecff9.hcp.canadacentral.azmk8s.io:443"},{"name":"KUBERNETES_SERVICE_HOST","value":"sonobuoy-test-dns-a72ecff9.hcp.canadacentral.azmk8s.io"}],"image":"mcr.microsoft.com/oss/kubernetes-csi/csi-node-driver-registrar:v2.5.0","imagePullPolicy":"IfNotPresent","livenessProbe":{"exec":{"command":["/csi-node-driver-registrar","--kubelet-registration-path=$(DRIVER_REG_SOCK_PATH)","--mode=kubelet-registration-probe"]},"failureThreshold":3,"initialDelaySeconds":60,"periodSeconds":10,"successThreshold":1,"timeoutSeconds":30},"name":"node-driver-registrar","resources":{"limits":{"memory":"100Mi"},"requests":{"cpu":"10m","memory":"20Mi"}},"terminationMessagePath":"/dev/termination-log","terminationMessagePolicy":"File","volumeMounts":[{"mountPath":"/csi","name":"socket-dir"},{"mountPath":"/registration","name":"registration-dir"},{"mountPath":"/var/run/secrets/kubernetes.io/serviceaccount","name":"kube-api-access-w2ddh","readOnly":true}]},{"args":["--v=5","--endpoint=$(CSI_ENDPOINT)","--nodeid=$(KUBE_NODE_NAME)","--metrics-address=0.0.0.0:29605","--enable-perf-optimization=true"],"env":[{"name":"AZURE_CREDENTIAL_FILE","value":"/etc/kubernetes/azure.json"},{"name":"CSI_ENDPOINT","value":"unix:///csi/csi.sock"},{"name":"KUBE_NODE_NAME","valueFrom":{"fieldRef":{"apiVersion":"v1","fieldPath":"spec.nodeName"}}},{"name":"KUBERNETES_PORT_443_TCP_ADDR","value":"sonobuoy-test-dns-a72ecff9.hcp.canadacentral.azmk8s.io"},{"name":"KUBERNETES_PORT","value":"tcp://sonobuoy-test-dns-a72ecff9.hcp.canadacentral.azmk8s.io:443"},{"name":"KUBERNETES_PORT_443_TCP","value":"tcp://sonobuoy-test-dns-a72ecff9.hcp.canadacentral.azmk8s.io:443"},{"name":"KUBERNETES_SERVICE_HOST","value":"sonobuoy-test-dns-a72ecff9.hcp.canadacentral.azmk8s.io"}],"image":"mcr.microsoft.com/oss/kubernetes-csi/azuredisk-csi:v1.19.0","imagePullPolicy":"IfNotPresent","livenessProbe":{"failureThreshold":5,"httpGet":{"path":"/healthz","port":"healthz","scheme":"HTTP"},"initialDelaySeconds":30,"periodSeconds":30,"successThreshold":1,"timeoutSeconds":10},"name":"azuredisk","ports":[{"containerPort":29603,"hostPort":29603,"name":"healthz","protocol":"TCP"}],"resources":{"limits":{"memory":"200Mi"},"requests":{"cpu":"10m","memory":"20Mi"}},"securityContext":{"privileged":true},"terminationMessagePath":"/dev/termination-log","terminationMessagePolicy":"File","volumeMounts":[{"mountPath":"/csi","name":"socket-dir"},{"mountPath":"/var/lib/kubelet/","mountPropagation":"Bidirectional","name":"mountpoint-dir"},{"mountPath":"/etc/kubernetes/","name":"azure-cred"},{"mountPath":"/dev","name":"device-dir"},{"mountPath":"/sys/bus/scsi/devices","name":"sys-devices-dir"},{"mountPath":"/sys/class/scsi_host/","name":"scsi-host-dir"},{"mountPath":"/var/run/secrets/kubernetes.io/serviceaccount","name":"kube-api-access-w2ddh","readOnly":true}]}],"dnsPolicy":"Default","enableServiceLinks":true,"hostNetwork":true,"nodeName":"aks-agentpool-16430811-vmss000002","preemptionPolicy":"PreemptLowerPriority","priority":2000001000,"priorityClassName":"system-node-critical","restartPolicy":"Always","schedulerName":"default-scheduler","securityContext":{},"serviceAccount":"csi-azuredisk-node-sa","serviceAccountName":"csi-azuredisk-node-sa","terminationGracePeriodSeconds":30,"tolerations":[{"key":"CriticalAddonsOnly","operator":"Exists"},{"effect":"NoExecute","operator":"Exists"},{"effect":"NoSchedule","operator":"Exists"}],"volumes":[{"hostPath":{"path":"/var/lib/kubelet/plugins/disk.csi.azure.com","type":"DirectoryOrCreate"},"name":"socket-dir"},{"hostPath":{"path":"/var/lib/kubelet/","type":"DirectoryOrCreate"},"name":"mountpoint-dir"},{"hostPath":{"path":"/var/lib/kubelet/plugins_registry/","type":"DirectoryOrCreate"},"name":"registration-dir"},{"hostPath":{"path":"/etc/kubernetes/","type":"DirectoryOrCreate"},"name":"azure-cred"},{"hostPath":{"path":"/dev","type":"Directory"},"name":"device-dir"},{"hostPath":{"path":"/sys/bus/scsi/devices","type":"Directory"},"name":"sys-devices-dir"},{"hostPath":{"path":"/sys/class/scsi_host/","type":"Directory"},"name":"scsi-host-dir"},{"name":"kube-api-access-w2ddh","projected":{"defaultMode":420,"sources":[{"serviceAccountToken":{"expirationSeconds":3607,"path":"token"}},{"configMap":{"items":[{"key":"ca.crt","path":"ca.crt"}],"name":"kube-root-ca.crt"}},{"downwardAPI":{"items":[{"fieldRef":{"apiVersion":"v1","fieldPath":"metadata.namespace"},"path":"namespace"}]}}]}}]},"status":{"conditions":[{"lastProbeTime":null,"lastTransitionTime":"2022-07-23T14:10:55Z","status":"True","type":"Initialized"},{"lastProbeTime":null,"lastTransitionTime":"2022-07-23T14:11:01Z","status":"True","type":"Ready"},{"lastProbeTime":null,"lastTransitionTime":"2022-07-23T14:11:01Z","status":"True","type":"ContainersReady"},{"lastProbeTime":null,"lastTransitionTime":"2022-07-23T14:10:54Z","status":"True","type":"PodScheduled"}],"containerStatuses":[{"containerID":"containerd://005c019bdad267d692083bf025adf18e623039bb9269b4f8b1f0677faad44498","image":"mcr.microsoft.com/oss/kubernetes-csi/azuredisk-csi:v1.19.0","imageID":"sha256:ac22fdb72ecbd041975c4eda18662fb2aa1d974b01716c372b77b828b0c49dd0","lastState":{},"name":"azuredisk","ready":true,"restartCount":0,"started":true,"state":{"running":{"startedAt":"2022-07-23T14:11:00Z"}}},{"containerID":"containerd://b73225800497b46195c633c60c0e1378e8e36be3cb2b22815ebc9aab139d0ea7","image":"mcr.microsoft.com/oss/kubernetes-csi/livenessprobe:v2.6.0","imageID":"sha256:f97059c7b56f8e771da0f91e81e495d8f722125c1342148db5970be7b4c16570","lastState":{},"name":"liveness-probe","ready":true,"restartCount":0,"started":true,"state":{"running":{"startedAt":"2022-07-23T14:10:58Z"}}},{"containerID":"containerd://44f5bdf481838d841a55a406e442cca5ccce9cf2730395a318f01d9ee803d47f","image":"mcr.microsoft.com/oss/kubernetes-csi/csi-node-driver-registrar:v2.5.0","imageID":"sha256:9f080292bc0292635062a424791004c647437fd6cb107580beeb946673d399c8","lastState":{},"name":"node-driver-registrar","ready":true,"restartCount":0,"started":true,"state":{"running":{"startedAt":"2022-07-23T14:10:59Z"}}}],"hostIP":"10.224.0.6","phase":"Running","podIP":"10.224.0.6","podIPs":[{"ip":"10.224.0.6"}],"qosClass":"Burstable","startTime":"2022-07-23T14:10:55Z"}},{"apiVersion":"v1","kind":"Pod","metadata":{"creationTimestamp":"2022-07-23T14:10:54Z","generateName":"csi-azurefile-node-","labels":{"app":"csi-azurefile-node","controller-revision-hash":"6775b679f9","pod-template-generation":"1"},"name":"csi-azurefile-node-mghwg","namespace":"kube-system","ownerReferences":[{"apiVersion":"apps/v1","blockOwnerDeletion":true,"controller":true,"kind":"DaemonSet","name":"csi-azurefile-node","uid":"91b68c4d-d851-4238-91bc-3587de4d0dd2"}],"resourceVersion":"993","uid":"a708e592-e474-4afa-b7b8-e3034cb3f8e8"},"spec":{"affinity":{"nodeAffinity":{"requiredDuringSchedulingIgnoredDuringExecution":{"nodeSelectorTerms":[{"matchFields":[{"key":"metadata.name","operator":"In","values":["aks-agentpool-16430811-vmss000002"]}]}]}}},"containers":[{"args":["--csi-address=/csi/csi.sock","--probe-timeout=3s","--health-port=29613","--v=2"],"env":[{"name":"KUBERNETES_PORT_443_TCP_ADDR","value":"sonobuoy-test-dns-a72ecff9.hcp.canadacentral.azmk8s.io"},{"name":"KUBERNETES_PORT","value":"tcp://sonobuoy-test-dns-a72ecff9.hcp.canadacentral.azmk8s.io:443"},{"name":"KUBERNETES_PORT_443_TCP","value":"tcp://sonobuoy-test-dns-a72ecff9.hcp.canadacentral.azmk8s.io:443"},{"name":"KUBERNETES_SERVICE_HOST","value":"sonobuoy-test-dns-a72ecff9.hcp.canadacentral.azmk8s.io"}],"image":"mcr.microsoft.com/oss/kubernetes-csi/livenessprobe:v2.6.0","imagePullPolicy":"IfNotPresent","name":"liveness-probe","resources":{"limits":{"memory":"100Mi"},"requests":{"cpu":"10m","memory":"20Mi"}},"terminationMessagePath":"/dev/termination-log","terminationMessagePolicy":"File","volumeMounts":[{"mountPath":"/csi","name":"socket-dir"},{"mountPath":"/var/run/secrets/kubernetes.io/serviceaccount","name":"kube-api-access-shj98","readOnly":true}]},{"args":["--csi-address=$(ADDRESS)","--kubelet-registration-path=$(DRIVER_REG_SOCK_PATH)","--v=2"],"env":[{"name":"ADDRESS","value":"/csi/csi.sock"},{"name":"DRIVER_REG_SOCK_PATH","value":"/var/lib/kubelet/plugins/file.csi.azure.com/csi.sock"},{"name":"KUBERNETES_PORT_443_TCP_ADDR","value":"sonobuoy-test-dns-a72ecff9.hcp.canadacentral.azmk8s.io"},{"name":"KUBERNETES_PORT","value":"tcp://sonobuoy-test-dns-a72ecff9.hcp.canadacentral.azmk8s.io:443"},{"name":"KUBERNETES_PORT_443_TCP","value":"tcp://sonobuoy-test-dns-a72ecff9.hcp.canadacentral.azmk8s.io:443"},{"name":"KUBERNETES_SERVICE_HOST","value":"sonobuoy-test-dns-a72ecff9.hcp.canadacentral.azmk8s.io"}],"image":"mcr.microsoft.com/oss/kubernetes-csi/csi-node-driver-registrar:v2.5.0","imagePullPolicy":"IfNotPresent","livenessProbe":{"exec":{"command":["/csi-node-driver-registrar","--kubelet-registration-path=$(DRIVER_REG_SOCK_PATH)","--mode=kubelet-registration-probe"]},"failureThreshold":3,"initialDelaySeconds":60,"periodSeconds":10,"successThreshold":1,"timeoutSeconds":30},"name":"node-driver-registrar","resources":{"limits":{"memory":"100Mi"},"requests":{"cpu":"10m","memory":"20Mi"}},"terminationMessagePath":"/dev/termination-log","terminationMessagePolicy":"File","volumeMounts":[{"mountPath":"/csi","name":"socket-dir"},{"mountPath":"/registration","name":"registration-dir"},{"mountPath":"/var/run/secrets/kubernetes.io/serviceaccount","name":"kube-api-access-shj98","readOnly":true}]},{"args":["--v=2","--endpoint=$(CSI_ENDPOINT)","--nodeid=$(KUBE_NODE_NAME)","--metrics-address=0.0.0.0:29615","--enable-get-volume-stats=true","--mount-permissions=0777"],"env":[{"name":"AZURE_CREDENTIAL_FILE","value":"/etc/kubernetes/azure.json"},{"name":"CSI_ENDPOINT","value":"unix:///csi/csi.sock"},{"name":"KUBE_NODE_NAME","valueFrom":{"fieldRef":{"apiVersion":"v1","fieldPath":"spec.nodeName"}}},{"name":"KUBERNETES_PORT_443_TCP_ADDR","value":"sonobuoy-test-dns-a72ecff9.hcp.canadacentral.azmk8s.io"},{"name":"KUBERNETES_PORT","value":"tcp://sonobuoy-test-dns-a72ecff9.hcp.canadacentral.azmk8s.io:443"},{"name":"KUBERNETES_PORT_443_TCP","value":"tcp://sonobuoy-test-dns-a72ecff9.hcp.canadacentral.azmk8s.io:443"},{"name":"KUBERNETES_SERVICE_HOST","value":"sonobuoy-test-dns-a72ecff9.hcp.canadacentral.azmk8s.io"}],"image":"mcr.microsoft.com/oss/kubernetes-csi/azurefile-csi:v1.19.0","imagePullPolicy":"IfNotPresent","livenessProbe":{"failureThreshold":5,"httpGet":{"path":"/healthz","port":"healthz","scheme":"HTTP"},"initialDelaySeconds":30,"periodSeconds":30,"successThreshold":1,"timeoutSeconds":10},"name":"azurefile","ports":[{"containerPort":29613,"hostPort":29613,"name":"healthz","protocol":"TCP"}],"resources":{"limits":{"memory":"400Mi"},"requests":{"cpu":"10m","memory":"20Mi"}},"securityContext":{"privileged":true},"terminationMessagePath":"/dev/termination-log","terminationMessagePolicy":"File","volumeMounts":[{"mountPath":"/csi","name":"socket-dir"},{"mountPath":"/var/lib/kubelet/","mountPropagation":"Bidirectional","name":"mountpoint-dir"},{"mountPath":"/etc/kubernetes/","name":"azure-cred"},{"mountPath":"/dev","name":"device-dir"},{"mountPath":"/var/run/secrets/kubernetes.io/serviceaccount","name":"kube-api-access-shj98","readOnly":true}]}],"dnsPolicy":"Default","enableServiceLinks":true,"hostNetwork":true,"nodeName":"aks-agentpool-16430811-vmss000002","preemptionPolicy":"PreemptLowerPriority","priority":2000001000,"priorityClassName":"system-node-critical","restartPolicy":"Always","schedulerName":"default-scheduler","securityContext":{},"serviceAccount":"csi-azurefile-node-sa","serviceAccountName":"csi-azurefile-node-sa","terminationGracePeriodSeconds":30,"tolerations":[{"key":"CriticalAddonsOnly","operator":"Exists"},{"effect":"NoExecute","operator":"Exists"},{"effect":"NoSchedule","operator":"Exists"}],"volumes":[{"hostPath":{"path":"/var/lib/kubelet/plugins/file.csi.azure.com","type":"DirectoryOrCreate"},"name":"socket-dir"},{"hostPath":{"path":"/var/lib/kubelet/","type":"DirectoryOrCreate"},"name":"mountpoint-dir"},{"hostPath":{"path":"/var/lib/kubelet/plugins_registry/","type":"DirectoryOrCreate"},"name":"registration-dir"},{"hostPath":{"path":"/etc/kubernetes/","type":"DirectoryOrCreate"},"name":"azure-cred"},{"hostPath":{"path":"/dev","type":"Directory"},"name":"device-dir"},{"name":"kube-api-access-shj98","projected":{"defaultMode":420,"sources":[{"serviceAccountToken":{"expirationSeconds":3607,"path":"token"}},{"configMap":{"items":[{"key":"ca.crt","path":"ca.crt"}],"name":"kube-root-ca.crt"}},{"downwardAPI":{"items":[{"fieldRef":{"apiVersion":"v1","fieldPath":"metadata.namespace"},"path":"namespace"}]}}]}}]},"status":{"conditions":[{"lastProbeTime":null,"lastTransitionTime":"2022-07-23T14:10:55Z","status":"True","type":"Initialized"},{"lastProbeTime":null,"lastTransitionTime":"2022-07-23T14:11:01Z","status":"True","type":"Ready"},{"lastProbeTime":null,"lastTransitionTime":"2022-07-23T14:11:01Z","status":"True","type":"ContainersReady"},{"lastProbeTime":null,"lastTransitionTime":"2022-07-23T14:10:54Z","status":"True","type":"PodScheduled"}],"containerStatuses":[{"containerID":"containerd://78efec09e254c2762fd9bdc1f230c53644bcc09b1fb9db76954899a7098ab001","image":"mcr.microsoft.com/oss/kubernetes-csi/azurefile-csi:v1.19.0","imageID":"sha256:7fd45772c079b14ca17d314ff7deb0a7c648b41ed2b913ab97483b40dd7981e7","lastState":{},"name":"azurefile","ready":true,"restartCount":0,"started":true,"state":{"running":{"startedAt":"2022-07-23T14:11:01Z"}}},{"containerID":"containerd://2ca32c53ee213ee8c59c79b96bb2bde51db7447abb0ebc49761fcacc0356913b","image":"mcr.microsoft.com/oss/kubernetes-csi/livenessprobe:v2.6.0","imageID":"sha256:f97059c7b56f8e771da0f91e81e495d8f722125c1342148db5970be7b4c16570","lastState":{},"name":"liveness-probe","ready":true,"restartCount":0,"started":true,"state":{"running":{"startedAt":"2022-07-23T14:10:59Z"}}},{"containerID":"containerd://291dadc71c94dd820d252261041f922f73b458133794bbc49e09bcdda2dcb342","image":"mcr.microsoft.com/oss/kubernetes-csi/csi-node-driver-registrar:v2.5.0","imageID":"sha256:9f080292bc0292635062a424791004c647437fd6cb107580beeb946673d399c8","lastState":{},"name":"node-driver-registrar","ready":true,"restartCount":0,"started":true,"state":{"running":{"startedAt":"2022-07-23T14:11:00Z"}}}],"hostIP":"10.224.0.6","phase":"Running","podIP":"10.224.0.6","podIPs":[{"ip":"10.224.0.6"}],"qosClass":"Burstable","startTime":"2022-07-23T14:10:55Z"}},{"apiVersion":"v1","kind":"Pod","metadata":{"annotations":{"checksum/client-cert":"bd46492bf0bb422a4a261940a97d545afee0b13872e6456ec557d59a9e010d90","checksum/service-account-key":"ac9a0ad8ebf545ad7d0c18b1279fab58134940aa694e387d61925a25cbb52497"},"creationTimestamp":"2022-07-23T14:26:47Z","generateName":"konnectivity-agent-6f87dbccc6-","labels":{"app":"konnectivity-agent","component":"tunnel","pod-template-hash":"6f87dbccc6"},"name":"konnectivity-agent-6f87dbccc6-9sx24","namespace":"kube-system","ownerReferences":[{"apiVersion":"apps/v1","blockOwnerDeletion":true,"controller":true,"kind":"ReplicaSet","name":"konnectivity-agent-6f87dbccc6","uid":"387cecdc-7aff-40c9-8a02-a138771b2b79"}],"resourceVersion":"5153","uid":"e0c18376-e2ea-447a-a9d8-1d05e41c9d5a"},"spec":{"affinity":{"nodeAffinity":{"preferredDuringSchedulingIgnoredDuringExecution":[{"preference":{"matchExpressions":[{"key":"kubernetes.azure.com/mode","operator":"In","values":["system"]}]},"weight":100}]},"podAntiAffinity":{"preferredDuringSchedulingIgnoredDuringExecution":[{"podAffinityTerm":{"labelSelector":{"matchExpressions":[{"key":"app","operator":"In","values":["konnectivity-agent"]}]},"topologyKey":"failure-domain.beta.kubernetes.io/zone"},"weight":10},{"podAffinityTerm":{"labelSelector":{"matchExpressions":[{"key":"app","operator":"In","values":["konnectivity-agent"]}]},"topologyKey":"kubernetes.io/hostname"},"weight":5}]}},"automountServiceAccountToken":false,"containers":[{"args":["--proxy-server-host=sonobuoy-test-dns-a72ecff9.hcp.canadacentral.azmk8s.io","--proxy-server-port=443","--health-server-port=8082","--keepalive-time=30s","--agent-key=/certs/client.key","--agent-cert=/certs/client.crt","--ca-cert=/certs/ca.crt","--alpn-proto=konnectivity","-v=2"],"command":["/proxy-agent"],"env":[{"name":"KUBERNETES_PORT_443_TCP_ADDR","value":"sonobuoy-test-dns-a72ecff9.hcp.canadacentral.azmk8s.io"},{"name":"KUBERNETES_PORT","value":"tcp://sonobuoy-test-dns-a72ecff9.hcp.canadacentral.azmk8s.io:443"},{"name":"KUBERNETES_PORT_443_TCP","value":"tcp://sonobuoy-test-dns-a72ecff9.hcp.canadacentral.azmk8s.io:443"},{"name":"KUBERNETES_SERVICE_HOST","value":"sonobuoy-test-dns-a72ecff9.hcp.canadacentral.azmk8s.io"}],"image":"mcr.microsoft.com/oss/kubernetes/apiserver-network-proxy/agent:v0.0.30","imagePullPolicy":"IfNotPresent","livenessProbe":{"failureThreshold":3,"httpGet":{"path":"/ready","port":8082,"scheme":"HTTP"},"initialDelaySeconds":30,"periodSeconds":60,"successThreshold":1,"timeoutSeconds":60},"name":"konnectivity-agent","readinessProbe":{"failureThreshold":3,"httpGet":{"path":"/ready","port":8082,"scheme":"HTTP"},"periodSeconds":10,"successThreshold":1,"timeoutSeconds":1},"resources":{"limits":{"cpu":"100m","memory":"128Mi"},"requests":{"cpu":"20m","memory":"20Mi"}},"terminationMessagePath":"/dev/termination-log","terminationMessagePolicy":"File","volumeMounts":[{"mountPath":"/certs","name":"certs"}]}],"dnsPolicy":"Default","enableServiceLinks":true,"nodeName":"aks-agentpool-16430811-vmss000002","nodeSelector":{"beta.kubernetes.io/os":"linux"},"preemptionPolicy":"PreemptLowerPriority","priority":2000001000,"priorityClassName":"system-node-critical","restartPolicy":"Always","schedulerName":"default-scheduler","securityContext":{},"serviceAccount":"konnectivity-agent","serviceAccountName":"konnectivity-agent","terminationGracePeriodSeconds":30,"tolerations":[{"key":"CriticalAddonsOnly","operator":"Exists"},{"effect":"NoExecute","key":"node.kubernetes.io/unreachable","operator":"Exists","tolerationSeconds":30},{"effect":"NoExecute","key":"node.kubernetes.io/not-ready","operator":"Exists","tolerationSeconds":30},{"effect":"NoSchedule","key":"node.kubernetes.io/memory-pressure","operator":"Exists"}],"volumes":[{"name":"certs","secret":{"defaultMode":420,"secretName":"konnectivity-certs"}}]},"status":{"conditions":[{"lastProbeTime":null,"lastTransitionTime":"2022-07-23T14:26:47Z","status":"True","type":"Initialized"},{"lastProbeTime":null,"lastTransitionTime":"2022-07-23T14:26:48Z","status":"True","type":"Ready"},{"lastProbeTime":null,"lastTransitionTime":"2022-07-23T14:26:48Z","status":"True","type":"ContainersReady"},{"lastProbeTime":null,"lastTransitionTime":"2022-07-23T14:26:47Z","status":"True","type":"PodScheduled"}],"containerStatuses":[{"containerID":"containerd://176ba32c303489f7be2e17ca0d959cd8bd1e302e4252e81995fdb7a1ce8fb155","image":"mcr.microsoft.com/oss/kubernetes/apiserver-network-proxy/agent:v0.0.30","imageID":"sha256:f450da74f8249b03b9ba503aed475a686dff63c934027b16cbb39054294cf931","lastState":{},"name":"konnectivity-agent","ready":true,"restartCount":0,"started":true,"state":{"running":{"startedAt":"2022-07-23T14:26:48Z"}}}],"hostIP":"10.224.0.6","phase":"Running","podIP":"10.244.1.6","podIPs":[{"ip":"10.244.1.6"}],"qosClass":"Burstable","startTime":"2022-07-23T14:26:47Z"}},{"apiVersion":"v1","kind":"Pod","metadata":{"annotations":{"checksum/client-cert":"bd46492bf0bb422a4a261940a97d545afee0b13872e6456ec557d59a9e010d90","checksum/service-account-key":"ac9a0ad8ebf545ad7d0c18b1279fab58134940aa694e387d61925a25cbb52497"},"creationTimestamp":"2022-07-23T14:09:45Z","generateName":"konnectivity-agent-6f87dbccc6-","labels":{"app":"konnectivity-agent","component":"tunnel","pod-template-hash":"6f87dbccc6"},"name":"konnectivity-agent-6f87dbccc6-pv2vc","namespace":"kube-system","ownerReferences":[{"apiVersion":"apps/v1","blockOwnerDeletion":true,"controller":true,"kind":"ReplicaSet","name":"konnectivity-agent-6f87dbccc6","uid":"387cecdc-7aff-40c9-8a02-a138771b2b79"}],"resourceVersion":"1249","uid":"f4c81dca-9266-48f2-a8b3-3767fbda9cf3"},"spec":{"affinity":{"nodeAffinity":{"preferredDuringSchedulingIgnoredDuringExecution":[{"preference":{"matchExpressions":[{"key":"kubernetes.azure.com/mode","operator":"In","values":["system"]}]},"weight":100}]},"podAntiAffinity":{"preferredDuringSchedulingIgnoredDuringExecution":[{"podAffinityTerm":{"labelSelector":{"matchExpressions":[{"key":"app","operator":"In","values":["konnectivity-agent"]}]},"topologyKey":"failure-domain.beta.kubernetes.io/zone"},"weight":10},{"podAffinityTerm":{"labelSelector":{"matchExpressions":[{"key":"app","operator":"In","values":["konnectivity-agent"]}]},"topologyKey":"kubernetes.io/hostname"},"weight":5}]}},"automountServiceAccountToken":false,"containers":[{"args":["--proxy-server-host=sonobuoy-test-dns-a72ecff9.hcp.canadacentral.azmk8s.io","--proxy-server-port=443","--health-server-port=8082","--keepalive-time=30s","--agent-key=/certs/client.key","--agent-cert=/certs/client.crt","--ca-cert=/certs/ca.crt","--alpn-proto=konnectivity","-v=2"],"command":["/proxy-agent"],"env":[{"name":"KUBERNETES_PORT_443_TCP_ADDR","value":"sonobuoy-test-dns-a72ecff9.hcp.canadacentral.azmk8s.io"},{"name":"KUBERNETES_PORT","value":"tcp://sonobuoy-test-dns-a72ecff9.hcp.canadacentral.azmk8s.io:443"},{"name":"KUBERNETES_PORT_443_TCP","value":"tcp://sonobuoy-test-dns-a72ecff9.hcp.canadacentral.azmk8s.io:443"},{"name":"KUBERNETES_SERVICE_HOST","value":"sonobuoy-test-dns-a72ecff9.hcp.canadacentral.azmk8s.io"}],"image":"mcr.microsoft.com/oss/kubernetes/apiserver-network-proxy/agent:v0.0.30","imagePullPolicy":"IfNotPresent","livenessProbe":{"failureThreshold":3,"httpGet":{"path":"/ready","port":8082,"scheme":"HTTP"},"initialDelaySeconds":30,"periodSeconds":60,"successThreshold":1,"timeoutSeconds":60},"name":"konnectivity-agent","readinessProbe":{"failureThreshold":3,"httpGet":{"path":"/ready","port":8082,"scheme":"HTTP"},"periodSeconds":10,"successThreshold":1,"timeoutSeconds":1},"resources":{"limits":{"cpu":"100m","memory":"128Mi"},"requests":{"cpu":"20m","memory":"20Mi"}},"terminationMessagePath":"/dev/termination-log","terminationMessagePolicy":"File","volumeMounts":[{"mountPath":"/certs","name":"certs"}]}],"dnsPolicy":"Default","enableServiceLinks":true,"nodeName":"aks-agentpool-16430811-vmss000002","nodeSelector":{"beta.kubernetes.io/os":"linux"},"preemptionPolicy":"PreemptLowerPriority","priority":2000001000,"priorityClassName":"system-node-critical","restartPolicy":"Always","schedulerName":"default-scheduler","securityContext":{},"serviceAccount":"konnectivity-agent","serviceAccountName":"konnectivity-agent","terminationGracePeriodSeconds":30,"tolerations":[{"key":"CriticalAddonsOnly","operator":"Exists"},{"effect":"NoExecute","key":"node.kubernetes.io/unreachable","operator":"Exists","tolerationSeconds":30},{"effect":"NoExecute","key":"node.kubernetes.io/not-ready","operator":"Exists","tolerationSeconds":30},{"effect":"NoSchedule","key":"node.kubernetes.io/memory-pressure","operator":"Exists"}],"volumes":[{"name":"certs","secret":{"defaultMode":420,"secretName":"konnectivity-certs"}}]},"status":{"conditions":[{"lastProbeTime":null,"lastTransitionTime":"2022-07-23T14:11:37Z","status":"True","type":"Initialized"},{"lastProbeTime":null,"lastTransitionTime":"2022-07-23T14:11:39Z","status":"True","type":"Ready"},{"lastProbeTime":null,"lastTransitionTime":"2022-07-23T14:11:39Z","status":"True","type":"ContainersReady"},{"lastProbeTime":null,"lastTransitionTime":"2022-07-23T14:11:37Z","status":"True","type":"PodScheduled"}],"containerStatuses":[{"containerID":"containerd://7456648d03a7e5b681c6e409432cfb70d3e94bdf9ba9f7f539aa8af945d5aa06","image":"mcr.microsoft.com/oss/kubernetes/apiserver-network-proxy/agent:v0.0.30","imageID":"sha256:f450da74f8249b03b9ba503aed475a686dff63c934027b16cbb39054294cf931","lastState":{},"name":"konnectivity-agent","ready":true,"restartCount":0,"started":true,"state":{"running":{"startedAt":"2022-07-23T14:11:38Z"}}}],"hostIP":"10.224.0.6","phase":"Running","podIP":"10.244.1.3","podIPs":[{"ip":"10.244.1.3"}],"qosClass":"Burstable","startTime":"2022-07-23T14:11:37Z"}},{"apiVersion":"v1","kind":"Pod","metadata":{"creationTimestamp":"2022-07-23T14:10:54Z","generateName":"kube-proxy-","labels":{"component":"kube-proxy","controller-revision-hash":"84588bb9d7","pod-template-generation":"1","tier":"node"},"name":"kube-proxy-wmw48","namespace":"kube-system","ownerReferences":[{"apiVersion":"apps/v1","blockOwnerDeletion":true,"controller":true,"kind":"DaemonSet","name":"kube-proxy","uid":"1a7fef5d-68d3-4414-9e15-49710b69e275"}],"resourceVersion":"983","uid":"437b7b8d-3d33-4f57-a5fa-3260bcd250b2"},"spec":{"affinity":{"nodeAffinity":{"requiredDuringSchedulingIgnoredDuringExecution":{"nodeSelectorTerms":[{"matchFields":[{"key":"metadata.name","operator":"In","values":["aks-agentpool-16430811-vmss000002"]}]}]}}},"containers":[{"command":["kube-proxy","--metrics-bind-address=0.0.0.0:10249","--kubeconfig=/var/lib/kubelet/kubeconfig","--cluster-cidr=10.244.0.0/16","--detect-local-mode=ClusterCIDR","--pod-interface-name-prefix=","--v=3"],"env":[{"name":"KUBERNETES_PORT_443_TCP_ADDR","value":"sonobuoy-test-dns-a72ecff9.hcp.canadacentral.azmk8s.io"},{"name":"KUBERNETES_PORT","value":"tcp://sonobuoy-test-dns-a72ecff9.hcp.canadacentral.azmk8s.io:443"},{"name":"KUBERNETES_PORT_443_TCP","value":"tcp://sonobuoy-test-dns-a72ecff9.hcp.canadacentral.azmk8s.io:443"},{"name":"KUBERNETES_SERVICE_HOST","value":"sonobuoy-test-dns-a72ecff9.hcp.canadacentral.azmk8s.io"}],"image":"mcr.microsoft.com/oss/kubernetes/kube-proxy:v1.23.8-hotfix.20220620.1","imagePullPolicy":"IfNotPresent","name":"kube-proxy","resources":{"requests":{"cpu":"100m"}},"securityContext":{"privileged":true},"terminationMessagePath":"/dev/termination-log","terminationMessagePolicy":"File","volumeMounts":[{"mountPath":"/var/lib/kubelet","name":"kubeconfig","readOnly":true},{"mountPath":"/etc/kubernetes/certs","name":"certificates","readOnly":true},{"mountPath":"/run/xtables.lock","name":"iptableslock"},{"mountPath":"/var/run/secrets/kubernetes.io/serviceaccount","name":"kube-api-access-zxjpn","readOnly":true}]}],"dnsPolicy":"ClusterFirst","enableServiceLinks":true,"hostNetwork":true,"nodeName":"aks-agentpool-16430811-vmss000002","preemptionPolicy":"PreemptLowerPriority","priority":2000001000,"priorityClassName":"system-node-critical","restartPolicy":"Always","schedulerName":"default-scheduler","securityContext":{},"serviceAccount":"kube-proxy","serviceAccountName":"kube-proxy","terminationGracePeriodSeconds":30,"tolerations":[{"key":"CriticalAddonsOnly","operator":"Exists"},{"effect":"NoExecute","operator":"Exists"},{"effect":"NoSchedule","operator":"Exists"}],"volumes":[{"hostPath":{"path":"/var/lib/kubelet","type":""},"name":"kubeconfig"},{"hostPath":{"path":"/etc/kubernetes/certs","type":""},"name":"certificates"},{"hostPath":{"path":"/run/xtables.lock","type":"FileOrCreate"},"name":"iptableslock"},{"name":"kube-api-access-zxjpn","projected":{"defaultMode":420,"sources":[{"serviceAccountToken":{"expirationSeconds":3607,"path":"token"}},{"configMap":{"items":[{"key":"ca.crt","path":"ca.crt"}],"name":"kube-root-ca.crt"}},{"downwardAPI":{"items":[{"fieldRef":{"apiVersion":"v1","fieldPath":"metadata.namespace"},"path":"namespace"}]}}]}}]},"status":{"conditions":[{"lastProbeTime":null,"lastTransitionTime":"2022-07-23T14:10:55Z","status":"True","type":"Initialized"},{"lastProbeTime":null,"lastTransitionTime":"2022-07-23T14:11:00Z","status":"True","type":"Ready"},{"lastProbeTime":null,"lastTransitionTime":"2022-07-23T14:11:00Z","status":"True","type":"ContainersReady"},{"lastProbeTime":null,"lastTransitionTime":"2022-07-23T14:10:54Z","status":"True","type":"PodScheduled"}],"containerStatuses":[{"containerID":"containerd://d3e2f441c9c3ca69857ea3761b24a72354a762ecb9fda643cfd2c46812275fde","image":"mcr.microsoft.com/oss/kubernetes/kube-proxy:v1.23.8-hotfix.20220620.1","imageID":"mcr.microsoft.com/oss/kubernetes/kube-proxy@sha256:e5acd422658067de34e30088a9bafd63a579f9ccf3f8a637583b13d19ddfe3c1","lastState":{},"name":"kube-proxy","ready":true,"restartCount":0,"started":true,"state":{"running":{"startedAt":"2022-07-23T14:11:00Z"}}}],"hostIP":"10.224.0.6","phase":"Running","podIP":"10.224.0.6","podIPs":[{"ip":"10.224.0.6"}],"qosClass":"Burstable","startTime":"2022-07-23T14:10:55Z"}},{"apiVersion":"v1","kind":"Pod","metadata":{"creationTimestamp":"2022-07-23T14:26:47Z","generateName":"metrics-server-6d594446f4-","labels":{"k8s-app":"metrics-server","pod-template-hash":"6d594446f4"},"name":"metrics-server-6d594446f4-c4tbw","namespace":"kube-system","ownerReferences":[{"apiVersion":"apps/v1","blockOwnerDeletion":true,"controller":true,"kind":"ReplicaSet","name":"metrics-server-6d594446f4","uid":"75c77ce8-3bfb-43f9-ba5c-36343183b187"}],"resourceVersion":"5529","uid":"9d2716f8-25ea-40d1-afe5-460c76e9970b"},"spec":{"affinity":{"nodeAffinity":{"preferredDuringSchedulingIgnoredDuringExecution":[{"preference":{"matchExpressions":[{"key":"kubernetes.azure.com/mode","operator":"In","values":["system"]}]},"weight":100}],"requiredDuringSchedulingIgnoredDuringExecution":{"nodeSelectorTerms":[{"matchExpressions":[{"key":"kubernetes.azure.com/cluster","operator":"Exists"}]}]}},"podAntiAffinity":{"preferredDuringSchedulingIgnoredDuringExecution":[{"podAffinityTerm":{"labelSelector":{"matchExpressions":[{"key":"k8s-app","operator":"In","values":["metrics-server"]}]},"topologyKey":"topology.kubernetes.io/zone"},"weight":10},{"podAffinityTerm":{"labelSelector":{"matchExpressions":[{"key":"k8s-app","operator":"In","values":["metrics-server"]}]},"topologyKey":"kubernetes.io/hostname"},"weight":5}]}},"containers":[{"command":["/metrics-server","--kubelet-insecure-tls","--kubelet-preferred-address-types=InternalIP","--tls-cipher-suites=TLS_ECDHE_RSA_WITH_AES_128_GCM_SHA256,TLS_ECDHE_ECDSA_WITH_AES_128_GCM_SHA256,TLS_ECDHE_RSA_WITH_AES_256_GCM_SHA384,TLS_ECDHE_ECDSA_WITH_AES_256_GCM_SHA384","--cert-dir=/tmp","--secure-port=4443"],"env":[{"name":"KUBERNETES_PORT_443_TCP_ADDR","value":"sonobuoy-test-dns-a72ecff9.hcp.canadacentral.azmk8s.io"},{"name":"KUBERNETES_PORT","value":"tcp://sonobuoy-test-dns-a72ecff9.hcp.canadacentral.azmk8s.io:443"},{"name":"KUBERNETES_PORT_443_TCP","value":"tcp://sonobuoy-test-dns-a72ecff9.hcp.canadacentral.azmk8s.io:443"},{"name":"KUBERNETES_SERVICE_HOST","value":"sonobuoy-test-dns-a72ecff9.hcp.canadacentral.azmk8s.io"}],"image":"mcr.microsoft.com/oss/kubernetes/metrics-server:v0.5.2","imagePullPolicy":"IfNotPresent","livenessProbe":{"failureThreshold":3,"httpGet":{"path":"/livez","port":"ms-https","scheme":"HTTPS"},"initialDelaySeconds":20,"periodSeconds":10,"successThreshold":1,"timeoutSeconds":10},"name":"metrics-server","ports":[{"containerPort":4443,"name":"ms-https","protocol":"TCP"}],"readinessProbe":{"failureThreshold":3,"httpGet":{"path":"/readyz","port":"ms-https","scheme":"HTTPS"},"initialDelaySeconds":60,"periodSeconds":10,"successThreshold":1,"timeoutSeconds":10},"resources":{"limits":{"cpu":"1","memory":"4G"},"requests":{"cpu":"44m","memory":"55Mi"}},"terminationMessagePath":"/dev/termination-log","terminationMessagePolicy":"File","volumeMounts":[{"mountPath":"/tmp","name":"tmp-dir"},{"mountPath":"/var/run/secrets/kubernetes.io/serviceaccount","name":"kube-api-access-qkkqp","readOnly":true}]}],"dnsPolicy":"ClusterFirst","enableServiceLinks":true,"nodeName":"aks-agentpool-16430811-vmss000002","nodeSelector":{"beta.kubernetes.io/os":"linux"},"preemptionPolicy":"PreemptLowerPriority","priority":2000001000,"priorityClassName":"system-node-critical","restartPolicy":"Always","schedulerName":"default-scheduler","securityContext":{},"serviceAccount":"metrics-server","serviceAccountName":"metrics-server","terminationGracePeriodSeconds":30,"tolerations":[{"key":"CriticalAddonsOnly","operator":"Exists"},{"effect":"NoExecute","key":"node.kubernetes.io/unreachable","operator":"Exists","tolerationSeconds":30},{"effect":"NoExecute","key":"node.kubernetes.io/not-ready","operator":"Exists","tolerationSeconds":30},{"effect":"NoSchedule","key":"node.kubernetes.io/memory-pressure","operator":"Exists"}],"volumes":[{"emptyDir":{},"name":"tmp-dir"},{"name":"kube-api-access-qkkqp","projected":{"defaultMode":420,"sources":[{"serviceAccountToken":{"expirationSeconds":3607,"path":"token"}},{"configMap":{"items":[{"key":"ca.crt","path":"ca.crt"}],"name":"kube-root-ca.crt"}},{"downwardAPI":{"items":[{"fieldRef":{"apiVersion":"v1","fieldPath":"metadata.namespace"},"path":"namespace"}]}}]}}]},"status":{"conditions":[{"lastProbeTime":null,"lastTransitionTime":"2022-07-23T14:26:47Z","status":"True","type":"Initialized"},{"lastProbeTime":null,"lastTransitionTime":"2022-07-23T14:27:57Z","status":"True","type":"Ready"},{"lastProbeTime":null,"lastTransitionTime":"2022-07-23T14:27:57Z","status":"True","type":"ContainersReady"},{"lastProbeTime":null,"lastTransitionTime":"2022-07-23T14:26:47Z","status":"True","type":"PodScheduled"}],"containerStatuses":[{"containerID":"containerd://b54dcd430f1a2d957550e591a9cd5a6a1fc23c5d1083be8793889ae572cc2eba","image":"mcr.microsoft.com/oss/kubernetes/metrics-server:v0.5.2","imageID":"sha256:80350116cf52bd5a5b3a17d12e05ad1d7b5d1ba9338d61c7a02bdbfc25cbfb49","lastState":{},"name":"metrics-server","ready":true,"restartCount":0,"started":true,"state":{"running":{"startedAt":"2022-07-23T14:26:48Z"}}}],"hostIP":"10.224.0.6","phase":"Running","podIP":"10.244.1.5","podIPs":[{"ip":"10.244.1.5"}],"qosClass":"Burstable","startTime":"2022-07-23T14:26:47Z"}},{"apiVersion":"v1","kind":"Pod","metadata":{"creationTimestamp":"2022-07-23T14:27:58Z","generateName":"metrics-server-6d594446f4-","labels":{"k8s-app":"metrics-server","pod-template-hash":"6d594446f4"},"name":"metrics-server-6d594446f4-rj4hm","namespace":"kube-system","ownerReferences":[{"apiVersion":"apps/v1","blockOwnerDeletion":true,"controller":true,"kind":"ReplicaSet","name":"metrics-server-6d594446f4","uid":"75c77ce8-3bfb-43f9-ba5c-36343183b187"}],"resourceVersion":"5812","uid":"2f5892ee-0178-46b9-9f30-d420953d64ab"},"spec":{"affinity":{"nodeAffinity":{"preferredDuringSchedulingIgnoredDuringExecution":[{"preference":{"matchExpressions":[{"key":"kubernetes.azure.com/mode","operator":"In","values":["system"]}]},"weight":100}],"requiredDuringSchedulingIgnoredDuringExecution":{"nodeSelectorTerms":[{"matchExpressions":[{"key":"kubernetes.azure.com/cluster","operator":"Exists"}]}]}},"podAntiAffinity":{"preferredDuringSchedulingIgnoredDuringExecution":[{"podAffinityTerm":{"labelSelector":{"matchExpressions":[{"key":"k8s-app","operator":"In","values":["metrics-server"]}]},"topologyKey":"topology.kubernetes.io/zone"},"weight":10},{"podAffinityTerm":{"labelSelector":{"matchExpressions":[{"key":"k8s-app","operator":"In","values":["metrics-server"]}]},"topologyKey":"kubernetes.io/hostname"},"weight":5}]}},"containers":[{"command":["/metrics-server","--kubelet-insecure-tls","--kubelet-preferred-address-types=InternalIP","--tls-cipher-suites=TLS_ECDHE_RSA_WITH_AES_128_GCM_SHA256,TLS_ECDHE_ECDSA_WITH_AES_128_GCM_SHA256,TLS_ECDHE_RSA_WITH_AES_256_GCM_SHA384,TLS_ECDHE_ECDSA_WITH_AES_256_GCM_SHA384","--cert-dir=/tmp","--secure-port=4443"],"env":[{"name":"KUBERNETES_PORT_443_TCP_ADDR","value":"sonobuoy-test-dns-a72ecff9.hcp.canadacentral.azmk8s.io"},{"name":"KUBERNETES_PORT","value":"tcp://sonobuoy-test-dns-a72ecff9.hcp.canadacentral.azmk8s.io:443"},{"name":"KUBERNETES_PORT_443_TCP","value":"tcp://sonobuoy-test-dns-a72ecff9.hcp.canadacentral.azmk8s.io:443"},{"name":"KUBERNETES_SERVICE_HOST","value":"sonobuoy-test-dns-a72ecff9.hcp.canadacentral.azmk8s.io"}],"image":"mcr.microsoft.com/oss/kubernetes/metrics-server:v0.5.2","imagePullPolicy":"IfNotPresent","livenessProbe":{"failureThreshold":3,"httpGet":{"path":"/livez","port":"ms-https","scheme":"HTTPS"},"initialDelaySeconds":20,"periodSeconds":10,"successThreshold":1,"timeoutSeconds":10},"name":"metrics-server","ports":[{"containerPort":4443,"name":"ms-https","protocol":"TCP"}],"readinessProbe":{"failureThreshold":3,"httpGet":{"path":"/readyz","port":"ms-https","scheme":"HTTPS"},"initialDelaySeconds":60,"periodSeconds":10,"successThreshold":1,"timeoutSeconds":10},"resources":{"limits":{"cpu":"1","memory":"4G"},"requests":{"cpu":"44m","memory":"55Mi"}},"terminationMessagePath":"/dev/termination-log","terminationMessagePolicy":"File","volumeMounts":[{"mountPath":"/tmp","name":"tmp-dir"},{"mountPath":"/var/run/secrets/kubernetes.io/serviceaccount","name":"kube-api-access-xmkzz","readOnly":true}]}],"dnsPolicy":"ClusterFirst","enableServiceLinks":true,"nodeName":"aks-agentpool-16430811-vmss000002","nodeSelector":{"beta.kubernetes.io/os":"linux"},"preemptionPolicy":"PreemptLowerPriority","priority":2000001000,"priorityClassName":"system-node-critical","restartPolicy":"Always","schedulerName":"default-scheduler","securityContext":{},"serviceAccount":"metrics-server","serviceAccountName":"metrics-server","terminationGracePeriodSeconds":30,"tolerations":[{"key":"CriticalAddonsOnly","operator":"Exists"},{"effect":"NoExecute","key":"node.kubernetes.io/unreachable","operator":"Exists","tolerationSeconds":30},{"effect":"NoExecute","key":"node.kubernetes.io/not-ready","operator":"Exists","tolerationSeconds":30},{"effect":"NoSchedule","key":"node.kubernetes.io/memory-pressure","operator":"Exists"}],"volumes":[{"emptyDir":{},"name":"tmp-dir"},{"name":"kube-api-access-xmkzz","projected":{"defaultMode":420,"sources":[{"serviceAccountToken":{"expirationSeconds":3607,"path":"token"}},{"configMap":{"items":[{"key":"ca.crt","path":"ca.crt"}],"name":"kube-root-ca.crt"}},{"downwardAPI":{"items":[{"fieldRef":{"apiVersion":"v1","fieldPath":"metadata.namespace"},"path":"namespace"}]}}]}}]},"status":{"conditions":[{"lastProbeTime":null,"lastTransitionTime":"2022-07-23T14:27:58Z","status":"True","type":"Initialized"},{"lastProbeTime":null,"lastTransitionTime":"2022-07-23T14:28:58Z","status":"True","type":"Ready"},{"lastProbeTime":null,"lastTransitionTime":"2022-07-23T14:28:58Z","status":"True","type":"ContainersReady"},{"lastProbeTime":null,"lastTransitionTime":"2022-07-23T14:27:58Z","status":"True","type":"PodScheduled"}],"containerStatuses":[{"containerID":"containerd://1aa57bb77f3dfd051296384bf5c37fb71911dd3799514b10dbff9147e47380f4","image":"mcr.microsoft.com/oss/kubernetes/metrics-server:v0.5.2","imageID":"sha256:80350116cf52bd5a5b3a17d12e05ad1d7b5d1ba9338d61c7a02bdbfc25cbfb49","lastState":{},"name":"metrics-server","ready":true,"restartCount":0,"started":true,"state":{"running":{"startedAt":"2022-07-23T14:27:58Z"}}}],"hostIP":"10.224.0.6","phase":"Running","podIP":"10.244.1.10","podIPs":[{"ip":"10.244.1.10"}],"qosClass":"Burstable","startTime":"2022-07-23T14:27:58Z"}},{"apiVersion":"v1","kind":"Pod","metadata":{"annotations":{"WSID":"MTNiZGRiOTctOTE1ZS00Zjg0LWJjOWMtNzRiMWE5ZmVhMmEz","agentVersion":"azure-mdsd-1.17.0","dockerProviderVersion":"18.0.1-0","kubernetes.azure.com/no-http-proxy-vars":"true","schema-versions":"v1"},"creationTimestamp":"2022-07-23T14:10:54Z","generateName":"omsagent-","labels":{"component":"oms-agent","controller-revision-hash":"85cf785ddf","kubernetes.azure.com/managedby":"aks","pod-template-generation":"1","tier":"node"},"name":"omsagent-bjsfm","namespace":"kube-system","ownerReferences":[{"apiVersion":"apps/v1","blockOwnerDeletion":true,"controller":true,"kind":"DaemonSet","name":"omsagent","uid":"208213c5-7229-4ee7-bcc8-5d1a22a9b444"}],"resourceVersion":"1001","uid":"b391faf5-8534-4526-acc6-dc92b505b7b4"},"spec":{"affinity":{"nodeAffinity":{"requiredDuringSchedulingIgnoredDuringExecution":{"nodeSelectorTerms":[{"matchFields":[{"key":"metadata.name","operator":"In","values":["aks-agentpool-16430811-vmss000002"]}]}]}}},"containers":[{"env":[{"name":"NODE_IP","valueFrom":{"fieldRef":{"apiVersion":"v1","fieldPath":"status.hostIP"}}},{"name":"FBIT_SERVICE_FLUSH_INTERVAL","value":"15"},{"name":"FBIT_TAIL_BUFFER_CHUNK_SIZE","value":"1"},{"name":"FBIT_TAIL_BUFFER_MAX_SIZE","value":"1"},{"name":"AKS_CLUSTER_NAME","value":"sonobuoy-test"},{"name":"AKS_RESOURCE_ID","value":"/subscriptions/ce859648-30e1-4135-9d0f-8358aebfe789/resourceGroups/sonobuoy-te_group/providers/Microsoft.ContainerService/managedClusters/sonobuoy-test"},{"name":"AKS_NODE_RESOURCE_GROUP","value":"MC_sonobuoy-te_group_sonobuoy-test_canadacentral"},{"name":"AKS_REGION","value":"canadacentral"},{"name":"CONTROLLER_TYPE","value":"DaemonSet"},{"name":"USER_ASSIGNED_IDENTITY_CLIENT_ID","value":"a02c4905-04be-41ca-85b6-32d86766e758"},{"name":"AZMON_CONTAINERLOGS_ONEAGENT_REGIONS","value":"koreacentral,norwayeast,eastus2"},{"name":"USING_AAD_MSI_AUTH","value":"false"},{"name":"KUBERNETES_PORT_443_TCP_ADDR","value":"sonobuoy-test-dns-a72ecff9.hcp.canadacentral.azmk8s.io"},{"name":"KUBERNETES_PORT","value":"tcp://sonobuoy-test-dns-a72ecff9.hcp.canadacentral.azmk8s.io:443"},{"name":"KUBERNETES_PORT_443_TCP","value":"tcp://sonobuoy-test-dns-a72ecff9.hcp.canadacentral.azmk8s.io:443"},{"name":"KUBERNETES_SERVICE_HOST","value":"sonobuoy-test-dns-a72ecff9.hcp.canadacentral.azmk8s.io"}],"image":"mcr.microsoft.com/azuremonitor/containerinsights/ciprod:ciprod06272022","imagePullPolicy":"IfNotPresent","livenessProbe":{"exec":{"command":["/bin/bash","-c","/opt/livenessprobe.sh"]},"failureThreshold":3,"initialDelaySeconds":60,"periodSeconds":60,"successThreshold":1,"timeoutSeconds":15},"name":"omsagent","ports":[{"containerPort":25225,"protocol":"TCP"},{"containerPort":25224,"protocol":"UDP"}],"resources":{"limits":{"cpu":"500m","memory":"750Mi"},"requests":{"cpu":"75m","memory":"325Mi"}},"securityContext":{"privileged":true},"terminationMessagePath":"/dev/termination-log","terminationMessagePolicy":"File","volumeMounts":[{"mountPath":"/hostfs","name":"host-root","readOnly":true},{"mountPath":"/var/run/host","name":"docker-sock"},{"mountPath":"/var/log","name":"host-log"},{"mountPath":"/var/lib/docker/containers","name":"containerlog-path","readOnly":true},{"mountPath":"/mnt/docker","name":"containerlog-path-2","readOnly":true},{"mountPath":"/mnt/containers","name":"containerlog-path-3","readOnly":true},{"mountPath":"/etc/kubernetes/host","name":"azure-json-path"},{"mountPath":"/etc/omsagent-secret","name":"omsagent-secret","readOnly":true},{"mountPath":"/etc/config/settings","name":"settings-vol-config","readOnly":true},{"mountPath":"/etc/config/settings/adx","name":"omsagent-adx-secret","readOnly":true},{"mountPath":"/var/run/secrets/kubernetes.io/serviceaccount","name":"kube-api-access-9dnwk","readOnly":true}]},{"env":[{"name":"NODE_IP","valueFrom":{"fieldRef":{"apiVersion":"v1","fieldPath":"status.hostIP"}}},{"name":"AKS_CLUSTER_NAME","value":"sonobuoy-test"},{"name":"AKS_RESOURCE_ID","value":"/subscriptions/ce859648-30e1-4135-9d0f-8358aebfe789/resourceGroups/sonobuoy-te_group/providers/Microsoft.ContainerService/managedClusters/sonobuoy-test"},{"name":"AKS_NODE_RESOURCE_GROUP","value":"MC_sonobuoy-te_group_sonobuoy-test_canadacentral"},{"name":"AKS_REGION","value":"canadacentral"},{"name":"CONTROLLER_TYPE","value":"DaemonSet"},{"name":"CONTAINER_TYPE","value":"PrometheusSidecar"},{"name":"USER_ASSIGNED_IDENTITY_CLIENT_ID","value":"a02c4905-04be-41ca-85b6-32d86766e758"},{"name":"USING_AAD_MSI_AUTH","value":"false"},{"name":"KUBERNETES_PORT_443_TCP_ADDR","value":"sonobuoy-test-dns-a72ecff9.hcp.canadacentral.azmk8s.io"},{"name":"KUBERNETES_PORT","value":"tcp://sonobuoy-test-dns-a72ecff9.hcp.canadacentral.azmk8s.io:443"},{"name":"KUBERNETES_PORT_443_TCP","value":"tcp://sonobuoy-test-dns-a72ecff9.hcp.canadacentral.azmk8s.io:443"},{"name":"KUBERNETES_SERVICE_HOST","value":"sonobuoy-test-dns-a72ecff9.hcp.canadacentral.azmk8s.io"}],"image":"mcr.microsoft.com/azuremonitor/containerinsights/ciprod:ciprod06272022","imagePullPolicy":"IfNotPresent","livenessProbe":{"exec":{"command":["/bin/bash","-c","/opt/livenessprobe.sh"]},"failureThreshold":3,"initialDelaySeconds":60,"periodSeconds":60,"successThreshold":1,"timeoutSeconds":15},"name":"omsagent-prometheus","resources":{"limits":{"cpu":"500m","memory":"1Gi"},"requests":{"cpu":"75m","memory":"225Mi"}},"securityContext":{"privileged":true},"terminationMessagePath":"/dev/termination-log","terminationMessagePolicy":"File","volumeMounts":[{"mountPath":"/etc/kubernetes/host","name":"azure-json-path"},{"mountPath":"/etc/omsagent-secret","name":"omsagent-secret","readOnly":true},{"mountPath":"/etc/config/settings","name":"settings-vol-config","readOnly":true},{"mountPath":"/etc/config/osm-settings","name":"osm-settings-vol-config","readOnly":true},{"mountPath":"/var/run/secrets/kubernetes.io/serviceaccount","name":"kube-api-access-9dnwk","readOnly":true}]}],"dnsConfig":{"options":[{"name":"ndots","value":"3"}]},"dnsPolicy":"ClusterFirst","enableServiceLinks":true,"nodeName":"aks-agentpool-16430811-vmss000002","preemptionPolicy":"PreemptLowerPriority","priority":2000001000,"priorityClassName":"system-node-critical","restartPolicy":"Always","schedulerName":"default-scheduler","securityContext":{},"serviceAccount":"omsagent","serviceAccountName":"omsagent","terminationGracePeriodSeconds":30,"tolerations":[{"key":"CriticalAddonsOnly","operator":"Exists"},{"effect":"NoExecute","operator":"Exists"},{"effect":"NoSchedule","operator":"Exists"},{"effect":"PreferNoSchedule","operator":"Exists"}],"volumes":[{"hostPath":{"path":"/","type":""},"name":"host-root"},{"hostPath":{"path":"/var/run","type":""},"name":"docker-sock"},{"hostPath":{"path":"/etc/hostname","type":""},"name":"container-hostname"},{"hostPath":{"path":"/var/log","type":""},"name":"host-log"},{"hostPath":{"path":"/var/lib/docker/containers","type":""},"name":"containerlog-path"},{"hostPath":{"path":"/mnt/docker","type":""},"name":"containerlog-path-2"},{"hostPath":{"path":"/mnt/containers","type":""},"name":"containerlog-path-3"},{"hostPath":{"path":"/etc/kubernetes","type":""},"name":"azure-json-path"},{"name":"omsagent-secret","secret":{"defaultMode":420,"secretName":"omsagent-secret"}},{"configMap":{"defaultMode":420,"name":"container-azm-ms-agentconfig","optional":true},"name":"settings-vol-config"},{"name":"omsagent-adx-secret","secret":{"defaultMode":420,"optional":true,"secretName":"omsagent-adx-secret"}},{"configMap":{"defaultMode":420,"name":"container-azm-ms-osmconfig","optional":true},"name":"osm-settings-vol-config"},{"name":"kube-api-access-9dnwk","projected":{"defaultMode":420,"sources":[{"serviceAccountToken":{"expirationSeconds":3607,"path":"token"}},{"configMap":{"items":[{"key":"ca.crt","path":"ca.crt"}],"name":"kube-root-ca.crt"}},{"downwardAPI":{"items":[{"fieldRef":{"apiVersion":"v1","fieldPath":"metadata.namespace"},"path":"namespace"}]}}]}}]},"status":{"conditions":[{"lastProbeTime":null,"lastTransitionTime":"2022-07-23T14:10:55Z","status":"True","type":"Initialized"},{"lastProbeTime":null,"lastTransitionTime":"2022-07-23T14:11:01Z","status":"True","type":"Ready"},{"lastProbeTime":null,"lastTransitionTime":"2022-07-23T14:11:01Z","status":"True","type":"ContainersReady"},{"lastProbeTime":null,"lastTransitionTime":"2022-07-23T14:10:54Z","status":"True","type":"PodScheduled"}],"containerStatuses":[{"containerID":"containerd://19c14e48b35106096e3c17ab2b7db37a42b95d011fc920ba84a9c3d7b6b712c0","image":"mcr.microsoft.com/azuremonitor/containerinsights/ciprod:ciprod06272022","imageID":"sha256:3f7d3baed45d927fa6ecc798aab1ca7534ba1a664e0650cf18b902e775e93ffc","lastState":{},"name":"omsagent","ready":true,"restartCount":0,"started":true,"state":{"running":{"startedAt":"2022-07-23T14:11:00Z"}}},{"containerID":"containerd://4a1b25cdd1d596405e389963294de26bdfdb89c526bd853188bc491b82eeed60","image":"mcr.microsoft.com/azuremonitor/containerinsights/ciprod:ciprod06272022","imageID":"sha256:3f7d3baed45d927fa6ecc798aab1ca7534ba1a664e0650cf18b902e775e93ffc","lastState":{},"name":"omsagent-prometheus","ready":true,"restartCount":0,"started":true,"state":{"running":{"startedAt":"2022-07-23T14:11:01Z"}}}],"hostIP":"10.224.0.6","phase":"Running","podIP":"10.244.1.2","podIPs":[{"ip":"10.244.1.2"}],"qosClass":"Burstable","startTime":"2022-07-23T14:10:55Z"}},{"apiVersion":"v1","kind":"Pod","metadata":{"annotations":{"WSID":"MTNiZGRiOTctOTE1ZS00Zjg0LWJjOWMtNzRiMWE5ZmVhMmEz","agentVersion":"azure-mdsd-1.17.0","cluster-autoscaler.kubernetes.io/safe-to-evict":"true","dockerProviderVersion":"18.0.1-0","kubernetes.azure.com/no-http-proxy-vars":"true","schema-versions":"v1"},"creationTimestamp":"2022-07-23T14:26:48Z","generateName":"omsagent-rs-7674dd6b5d-","labels":{"kubernetes.azure.com/managedby":"aks","pod-template-hash":"7674dd6b5d","rsName":"omsagent-rs"},"name":"omsagent-rs-7674dd6b5d-mnh2x","namespace":"kube-system","ownerReferences":[{"apiVersion":"apps/v1","blockOwnerDeletion":true,"controller":true,"kind":"ReplicaSet","name":"omsagent-rs-7674dd6b5d","uid":"fd02a59c-0cea-4288-a940-d2c1748769de"}],"resourceVersion":"5194","uid":"136f10e6-ced9-4d99-9449-8c7f5b2c8030"},"spec":{"affinity":{"nodeAffinity":{"preferredDuringSchedulingIgnoredDuringExecution":[{"preference":{"matchExpressions":[{"key":"kubernetes.azure.com/mode","operator":"In","values":["system"]}]},"weight":100},{"preference":{"matchExpressions":[{"key":"storageprofile","operator":"NotIn","values":["managed"]}]},"weight":1}],"requiredDuringSchedulingIgnoredDuringExecution":{"nodeSelectorTerms":[{"matchExpressions":[{"key":"beta.kubernetes.io/os","operator":"In","values":["linux"]},{"key":"kubernetes.io/role","operator":"In","values":["agent"]},{"key":"kubernetes.azure.com/cluster","operator":"Exists"},{"key":"type","operator":"NotIn","values":["virtual-kubelet"]}]}]}}},"containers":[{"env":[{"name":"NODE_IP","valueFrom":{"fieldRef":{"apiVersion":"v1","fieldPath":"status.hostIP"}}},{"name":"AKS_CLUSTER_NAME","value":"sonobuoy-test"},{"name":"AKS_RESOURCE_ID","value":"/subscriptions/ce859648-30e1-4135-9d0f-8358aebfe789/resourceGroups/sonobuoy-te_group/providers/Microsoft.ContainerService/managedClusters/sonobuoy-test"},{"name":"AKS_NODE_RESOURCE_GROUP","value":"MC_sonobuoy-te_group_sonobuoy-test_canadacentral"},{"name":"AKS_REGION","value":"canadacentral"},{"name":"CONTROLLER_TYPE","value":"ReplicaSet"},{"name":"USER_ASSIGNED_IDENTITY_CLIENT_ID","value":"a02c4905-04be-41ca-85b6-32d86766e758"},{"name":"NUM_OF_FLUENTD_WORKERS","valueFrom":{"resourceFieldRef":{"containerName":"omsagent","divisor":"0","resource":"limits.cpu"}}},{"name":"SIDECAR_SCRAPING_ENABLED","value":"true"},{"name":"USING_AAD_MSI_AUTH","value":"false"},{"name":"KUBERNETES_PORT_443_TCP_ADDR","value":"sonobuoy-test-dns-a72ecff9.hcp.canadacentral.azmk8s.io"},{"name":"KUBERNETES_PORT","value":"tcp://sonobuoy-test-dns-a72ecff9.hcp.canadacentral.azmk8s.io:443"},{"name":"KUBERNETES_PORT_443_TCP","value":"tcp://sonobuoy-test-dns-a72ecff9.hcp.canadacentral.azmk8s.io:443"},{"name":"KUBERNETES_SERVICE_HOST","value":"sonobuoy-test-dns-a72ecff9.hcp.canadacentral.azmk8s.io"}],"image":"mcr.microsoft.com/azuremonitor/containerinsights/ciprod:ciprod06272022","imagePullPolicy":"IfNotPresent","livenessProbe":{"exec":{"command":["/bin/bash","-c","/opt/livenessprobe.sh"]},"failureThreshold":3,"initialDelaySeconds":60,"periodSeconds":60,"successThreshold":1,"timeoutSeconds":15},"name":"omsagent","ports":[{"containerPort":25225,"protocol":"TCP"},{"containerPort":25224,"protocol":"UDP"},{"containerPort":25227,"name":"in-rs-tcp","protocol":"TCP"}],"resources":{"limits":{"cpu":"1","memory":"1Gi"},"requests":{"cpu":"150m","memory":"250Mi"}},"securityContext":{"privileged":true},"terminationMessagePath":"/dev/termination-log","terminationMessagePolicy":"File","volumeMounts":[{"mountPath":"/var/run/host","name":"docker-sock"},{"mountPath":"/var/log","name":"host-log"},{"mountPath":"/etc/kubernetes/host","name":"azure-json-path"},{"mountPath":"/etc/omsagent-secret","name":"omsagent-secret","readOnly":true},{"mountPath":"/etc/config","name":"omsagent-rs-config"},{"mountPath":"/etc/config/settings","name":"settings-vol-config","readOnly":true},{"mountPath":"/etc/config/settings/adx","name":"omsagent-adx-secret","readOnly":true},{"mountPath":"/etc/config/osm-settings","name":"osm-settings-vol-config","readOnly":true},{"mountPath":"/var/run/secrets/kubernetes.io/serviceaccount","name":"kube-api-access-22p6b","readOnly":true}]}],"dnsPolicy":"ClusterFirst","enableServiceLinks":true,"nodeName":"aks-agentpool-16430811-vmss000002","preemptionPolicy":"PreemptLowerPriority","priority":2000001000,"priorityClassName":"system-node-critical","restartPolicy":"Always","schedulerName":"default-scheduler","securityContext":{},"serviceAccount":"omsagent","serviceAccountName":"omsagent","terminationGracePeriodSeconds":30,"tolerations":[{"key":"CriticalAddonsOnly","operator":"Exists"},{"effect":"NoExecute","key":"node.kubernetes.io/not-ready","operator":"Exists","tolerationSeconds":300},{"effect":"NoExecute","key":"node.kubernetes.io/unreachable","operator":"Exists","tolerationSeconds":300},{"effect":"NoSchedule","key":"node.kubernetes.io/memory-pressure","operator":"Exists"}],"volumes":[{"hostPath":{"path":"/var/run","type":""},"name":"docker-sock"},{"hostPath":{"path":"/etc/hostname","type":""},"name":"container-hostname"},{"hostPath":{"path":"/var/log","type":""},"name":"host-log"},{"hostPath":{"path":"/etc/kubernetes","type":""},"name":"azure-json-path"},{"name":"omsagent-secret","secret":{"defaultMode":420,"secretName":"omsagent-secret"}},{"configMap":{"defaultMode":420,"name":"omsagent-rs-config"},"name":"omsagent-rs-config"},{"configMap":{"defaultMode":420,"name":"container-azm-ms-agentconfig","optional":true},"name":"settings-vol-config"},{"name":"omsagent-adx-secret","secret":{"defaultMode":420,"optional":true,"secretName":"omsagent-adx-secret"}},{"configMap":{"defaultMode":420,"name":"container-azm-ms-osmconfig","optional":true},"name":"osm-settings-vol-config"},{"name":"kube-api-access-22p6b","projected":{"defaultMode":420,"sources":[{"serviceAccountToken":{"expirationSeconds":3607,"path":"token"}},{"configMap":{"items":[{"key":"ca.crt","path":"ca.crt"}],"name":"kube-root-ca.crt"}},{"downwardAPI":{"items":[{"fieldRef":{"apiVersion":"v1","fieldPath":"metadata.namespace"},"path":"namespace"}]}}]}}]},"status":{"conditions":[{"lastProbeTime":null,"lastTransitionTime":"2022-07-23T14:26:48Z","status":"True","type":"Initialized"},{"lastProbeTime":null,"lastTransitionTime":"2022-07-23T14:26:50Z","status":"True","type":"Ready"},{"lastProbeTime":null,"lastTransitionTime":"2022-07-23T14:26:50Z","status":"True","type":"ContainersReady"},{"lastProbeTime":null,"lastTransitionTime":"2022-07-23T14:26:48Z","status":"True","type":"PodScheduled"}],"containerStatuses":[{"containerID":"containerd://321a610a43fd7c9c900cb2737b000d5d695fbf249d9073acc5c40fea93f42184","image":"mcr.microsoft.com/azuremonitor/containerinsights/ciprod:ciprod06272022","imageID":"sha256:3f7d3baed45d927fa6ecc798aab1ca7534ba1a664e0650cf18b902e775e93ffc","lastState":{},"name":"omsagent","ready":true,"restartCount":0,"started":true,"state":{"running":{"startedAt":"2022-07-23T14:26:49Z"}}}],"hostIP":"10.224.0.6","phase":"Running","podIP":"10.244.1.8","podIPs":[{"ip":"10.244.1.8"}],"qosClass":"Burstable","startTime":"2022-07-23T14:26:48Z"}}],"kind":"PodList","metadata":{"resourceVersion":"15221"}}
